{
 "code": "2923",
 "industry": "建材營造",
 "monthly": {
  "2014-12": {
   "revenue": 2566840.0
  },
  "2015-01": {
   "mom": -56.99,
   "revenue": 1103913.0
  },
  "2015-02": {
   "mom": -3.72,
   "revenue": 1062893.0
  },
  "2015-03": {
   "mom": 12.91,
   "revenue": 1200134.0
  },
  "2015-04": {
   "mom": -31.71,
   "revenue": 819628.0
  },
  "2015-05": {
   "mom": -26.91,
   "revenue": 599102.0
  },
  "2015-06": {
   "mom": 10.41,
   "revenue": 661484.0
  },
  "2015-07": {
   "mom": -6.11,
   "revenue": 621037.0
  },
  "2015-08": {
   "mom": 12.24,
   "revenue": 697043.0
  },
  "2015-09": {
   "mom": 385.35,
   "revenue": 3383118.0
  },
  "2015-10": {
   "mom": -63.09,
   "revenue": 1248600.0
  },
  "2015-11": {
   "mom": -39.52,
   "revenue": 755144.0
  },
  "2015-12": {
   "mom": -7.03,
   "revenue": 702056.0,
   "yoy": -72.65,
   "yoy_12m": -72.65,
   "yoy_3m": -72.65
  },
  "2016-01": {
   "mom": 58.24,
   "revenue": 1110922.0,
   "yoy": 0.63,
   "yoy_12m": -36.01,
   "yoy_3m": -36.01
  },
  "2016-02": {
   "mom": -49.51,
   "revenue": 560924.0,
   "yoy": -47.23,
   "yoy_12m": -39.75,
   "yoy_3m": -39.75
  },
  "2016-03": {
   "mom": -19.84,
   "revenue": 449625.0,
   "yoy": -62.54,
   "yoy_12m": -45.45,
   "yoy_3m": -36.38
  },
  "2016-04": {
   "mom": 11.57,
   "revenue": 501661.0,
   "yoy": -38.79,
   "yoy_12m": -44.12,
   "yoy_3m": -49.52
  },
  "2016-05": {
   "mom": -7.76,
   "revenue": 462717.0,
   "yoy": -22.76,
   "yoy_12m": -40.56,
   "yoy_3m": -41.36
  },
  "2016-06": {
   "mom": 9.28,
   "revenue": 505679.0,
   "yoy": -23.55,
   "yoy_12m": -38.13,
   "yoy_3m": -28.37
  },
  "2016-07": {
   "mom": -11.03,
   "revenue": 449898.0,
   "yoy": -27.56,
   "yoy_12m": -36.81,
   "yoy_3m": -24.62
  },
  "2016-08": {
   "mom": 10.62,
   "revenue": 497680.0,
   "yoy": -28.6,
   "yoy_12m": -35.89,
   "yoy_3m": -26.57
  },
  "2016-09": {
   "mom": -25.58,
   "revenue": 370378.0,
   "yoy": -89.05,
   "yoy_12m": -41.21,
   "yoy_3m": -48.4
  },
  "2016-10": {
   "mom": 5.18,
   "revenue": 389567.0,
   "yoy": -68.8,
   "yoy_12m": -43.72,
   "yoy_3m": -62.15
  },
  "2016-11": {
   "mom": 10.15,
   "revenue": 429095.0,
   "yoy": -43.18,
   "yoy_12m": -43.67,
   "yoy_3m": -67.01
  },
  "2016-12": {
   "mom": 294.42,
   "revenue": 1692444.0,
   "yoy": 141.07,
   "yoy_12m": -25.86,
   "yoy_3m": 9.7
  },
  "2017-01": {
   "mom": -69.24,
   "revenue": 520569.0,
   "yoy": -53.14,
   "yoy_12m": -30.34,
   "yoy_3m": 14.92
  },
  "2017-02": {
   "mom": -20.77,
   "revenue": 412470.0,
   "yoy": -26.47,
   "yoy_12m": -28.61,
   "yoy_3m": 20.49
  },
  "2017-03": {
   "mom": -5.0,
   "revenue": 391828.0,
   "yoy": -12.85,
   "yoy_12m": -24.47,
   "yoy_3m": -30.82
  },
  "2017-04": {
   "mom": -4.84,
   "revenue": 372853.0,
   "yoy": -25.68,
   "yoy_12m": -23.38,
   "yoy_3m": -21.67
  },
  "2017-05": {
   "mom": 7.26,
   "revenue": 399915.0,
   "yoy": -13.57,
   "yoy_12m": -22.61,
   "yoy_3m": -17.37
  },
  "2017-06": {
   "mom": -9.99,
   "revenue": 359962.0,
   "yoy": -28.82,
   "yoy_12m": -23.05,
   "yoy_3m": -22.69
  },
  "2017-07": {
   "mom": 2.39,
   "revenue": 368580.0,
   "yoy": -18.07,
   "yoy_12m": -22.26,
   "yoy_3m": -20.15
  },
  "2017-08": {
   "mom": 41.42,
   "revenue": 521242.0,
   "yoy": 4.73,
   "yoy_12m": -19.49,
   "yoy_3m": -14.05
  },
  "2017-09": {
   "mom": -17.48,
   "revenue": 430151.0,
   "yoy": 16.14,
   "yoy_12m": -10.72,
   "yoy_3m": 0.93
  },
  "2017-10": {
   "mom": -6.51,
   "revenue": 402130.0,
   "yoy": 3.22,
   "yoy_12m": -4.72,
   "yoy_3m": 8.03
  },
  "2017-11": {
   "mom": 1.14,
   "revenue": 406705.0,
   "yoy": -5.22,
   "yoy_12m": -1.56,
   "yoy_3m": 4.71
  },
  "2017-12": {
   "mom": 9.02,
   "revenue": 443383.0,
   "yoy": -73.8,
   "yoy_12m": -19.46,
   "yoy_3m": -25.27
  },
  "2018-01": {
   "mom": 7.98,
   "revenue": 478753.0,
   "yoy": -8.03,
   "yoy_12m": -15.7,
   "yoy_3m": -29.02
  },
  "2018-02": {
   "mom": -32.58,
   "revenue": 322760.0,
   "yoy": -21.75,
   "yoy_12m": -15.31,
   "yoy_3m": -34.53
  },
  "2018-03": {
   "mom": 28.01,
   "revenue": 413166.0,
   "yoy": 5.45,
   "yoy_12m": -13.78,
   "yoy_3m": -8.11
  },
  "2018-04": {
   "mom": -0.65,
   "revenue": 410495.0,
   "yoy": 10.1,
   "yoy_12m": -10.8,
   "yoy_3m": -2.07
  },
  "2018-05": {
   "mom": -8.42,
   "revenue": 375949.0,
   "yoy": -5.99,
   "yoy_12m": -10.17,
   "yoy_3m": 3.19
  },
  "2018-06": {
   "mom": 17.11,
   "revenue": 440274.0,
   "yoy": 22.31,
   "yoy_12m": -5.91,
   "yoy_3m": 8.81
  },
  "2018-07": {
   "mom": -8.43,
   "revenue": 403145.0,
   "yoy": 9.38,
   "yoy_12m": -3.62,
   "yoy_3m": 8.57
  },
  "2018-08": {
   "mom": -18.55,
   "revenue": 328378.0,
   "yoy": -37.0,
   "yoy_12m": -7.1,
   "yoy_3m": -1.77
  },
  "2018-09": {
   "mom": 24.74,
   "revenue": 409610.0,
   "yoy": -4.78,
   "yoy_12m": -8.84,
   "yoy_3m": -10.8
  },
  "2018-10": {
   "mom": 11.04,
   "revenue": 454844.0,
   "yoy": 13.11,
   "yoy_12m": -8.02,
   "yoy_3m": -9.56
  },
  "2018-11": {
   "mom": -19.37,
   "revenue": 366740.0,
   "yoy": -9.83,
   "yoy_12m": -8.4,
   "yoy_3m": -0.5
  },
  "2018-12": {
   "mom": 867.83,
   "revenue": 3549431.0,
   "yoy": 700.53,
   "yoy_12m": 56.12,
   "yoy_3m": 234.6
  },
  "2019-01": {
   "mom": -84.44,
   "revenue": 552276.0,
   "yoy": 15.36,
   "yoy_12m": 58.07,
   "yoy_3m": 235.35
  },
  "2019-02": {
   "mom": -53.04,
   "revenue": 259361.0,
   "yoy": -19.64,
   "yoy_12m": 58.25,
   "yoy_3m": 232.08
  },
  "2019-03": {
   "mom": 33.74,
   "revenue": 346858.0,
   "yoy": -16.05,
   "yoy_12m": 56.46,
   "yoy_3m": -6.78
  },
  "2019-04": {
   "mom": -33.95,
   "revenue": 229094.0,
   "yoy": -44.19,
   "yoy_12m": 51.93,
   "yoy_3m": -26.63
  },
  "2019-05": {
   "mom": 613.06,
   "revenue": 1633584.0,
   "yoy": 334.52,
   "yoy_12m": 80.31,
   "yoy_3m": 91.43
  },
  "2019-06": {
   "mom": -81.31,
   "revenue": 305298.0,
   "yoy": -30.66,
   "yoy_12m": 75.9,
   "yoy_3m": 86.56
  },
  "2019-07": {
   "mom": 6.38,
   "revenue": 324776.0,
   "yoy": -19.44,
   "yoy_12m": 73.49,
   "yoy_3m": 94.81
  },
  "2019-08": {
   "mom": -6.36,
   "revenue": 304115.0,
   "yoy": -7.39,
   "yoy_12m": 75.96,
   "yoy_3m": -19.16
  },
  "2019-09": {
   "mom": 30.56,
   "revenue": 397055.0,
   "yoy": -3.07,
   "yoy_12m": 76.1,
   "yoy_3m": -9.97
  },
  "2019-10": {
   "mom": -8.51,
   "revenue": 363285.0,
   "yoy": -20.13,
   "yoy_12m": 73.33,
   "yoy_3m": -10.2
  },
  "2019-11": {
   "mom": 33.11,
   "revenue": 483559.0,
   "yoy": 31.85,
   "yoy_12m": 76.81,
   "yoy_3m": 2.88
  },
  "2019-12": {
   "mom": 13.31,
   "revenue": 547924.0,
   "yoy": -84.56,
   "yoy_12m": 11.38,
   "yoy_3m": -24.28
  },
  "2020-01": {
   "mom": -4.8,
   "revenue": 521617.0,
   "yoy": -5.55,
   "yoy_12m": 9.64,
   "yoy_3m": -19.42
  },
  "2020-02": {
   "mom": -71.05,
   "revenue": 151003.0,
   "yoy": -41.78,
   "yoy_12m": 7.8,
   "yoy_3m": -43.96
  },
  "2020-03": {
   "mom": 223.04,
   "revenue": 487793.0,
   "yoy": 40.63,
   "yoy_12m": 12.52,
   "yoy_3m": -2.23
  },
  "2020-04": {
   "mom": 22.14,
   "revenue": 595799.0,
   "yoy": 160.07,
   "yoy_12m": 29.54,
   "yoy_3m": 52.97
  },
  "2020-05": {
   "mom": 202.15,
   "revenue": 1800231.0,
   "yoy": 10.2,
   "yoy_12m": 2.51,
   "yoy_3m": 70.3
  },
  "2020-06": {
   "mom": -41.23,
   "revenue": 1057909.0,
   "yoy": 246.52,
   "yoy_12m": 25.61,
   "yoy_3m": 138.93
  },
  "2020-07": {
   "mom": -39.89,
   "revenue": 635927.0,
   "yoy": 95.8,
   "yoy_12m": 35.22,
   "yoy_3m": 117.51
  },
  "2020-08": {
   "mom": -6.68,
   "revenue": 593417.0,
   "yoy": 95.13,
   "yoy_12m": 43.76,
   "yoy_3m": 145.82
  },
  "2020-09": {
   "mom": 849.91,
   "revenue": 5636921.0,
   "yoy": 1319.68,
   "yoy_12m": 153.99,
   "yoy_3m": 503.54
  },
  "2020-10": {
   "mom": -87.92,
   "revenue": 680940.0,
   "yoy": 87.44,
   "yoy_12m": 162.95,
   "yoy_3m": 500.75
  },
  "2020-11": {
   "mom": -25.92,
   "revenue": 504426.0,
   "yoy": 4.32,
   "yoy_12m": 160.66,
   "yoy_3m": 470.48
  },
  "2020-12": {
   "mom": 46.95,
   "revenue": 741250.0,
   "yoy": 35.28,
   "yoy_12m": 170.65,
   "yoy_3m": 42.35
  },
  "2021-01": {
   "mom": -40.55,
   "revenue": 440643.0,
   "yoy": -15.52,
   "yoy_12m": 169.81,
   "yoy_3m": 8.03
  },
  "2021-02": {
   "mom": -31.23,
   "revenue": 303028.0,
   "yoy": 100.68,
   "yoy_12m": 181.69,
   "yoy_3m": 40.15
  },
  "2021-03": {
   "mom": 98.17,
   "revenue": 600513.0,
   "yoy": 23.11,
   "yoy_12m": 180.23,
   "yoy_3m": 36.09
  },
  "2021-04": {
   "mom": -12.32,
   "revenue": 526548.0,
   "yoy": -11.62,
   "yoy_12m": 165.92,
   "yoy_3m": 37.39
  },
  "2021-05": {
   "mom": -25.49,
   "revenue": 392337.0,
   "yoy": -78.21,
   "yoy_12m": 158.55,
   "yoy_3m": -22.24
  },
  "2021-06": {
   "mom": -13.97,
   "revenue": 337526.0,
   "yoy": -68.09,
   "yoy_12m": 132.33,
   "yoy_3m": -52.64
  },
  "2021-07": {
   "mom": 72.28,
   "revenue": 581487.0,
   "yoy": -8.56,
   "yoy_12m": 123.64,
   "yoy_3m": -51.62
  },
  "2021-08": {
   "mom": -55.91,
   "revenue": 256361.0,
   "yoy": -56.8,
   "yoy_12m": 110.98,
   "yoy_3m": -44.48
  },
  "2021-09": {
   "mom": 27.91,
   "revenue": 327905.0,
   "yoy": -94.18,
   "yoy_12m": -6.85,
   "yoy_3m": -53.18
  },
  "2021-10": {
   "mom": -20.28,
   "revenue": 261399.0,
   "yoy": -61.61,
   "yoy_12m": -19.27,
   "yoy_3m": -70.86
  },
  "2021-11": {
   "mom": 33.94,
   "revenue": 350112.0,
   "yoy": -30.59,
   "yoy_12m": -22.18,
   "yoy_3m": -62.13
  },
  "2021-12": {
   "mom": 21.61,
   "revenue": 425757.0,
   "yoy": -42.56,
   "yoy_12m": -28.66,
   "yoy_3m": -44.92
  },
  "2022-01": {
   "mom": 17.59,
   "revenue": 500651.0,
   "yoy": 13.62,
   "yoy_12m": -26.23,
   "yoy_3m": -19.84
  },
  "2022-02": {
   "mom": 482.45,
   "revenue": 2916063.0,
   "yoy": 862.31,
   "yoy_12m": 37.23,
   "yoy_3m": 277.79
  },
  "2022-03": {
   "mom": -4.67,
   "revenue": 2779785.0,
   "yoy": 362.9,
   "yoy_12m": 65.55,
   "yoy_3m": 412.94
  },
  "2022-04": {
   "mom": -99.15,
   "revenue": 23667.0,
   "yoy": -95.51,
   "yoy_12m": 58.56,
   "yoy_3m": 376.57
  },
  "2022-05": {
   "mom": -12.25,
   "revenue": 20768.0,
   "yoy": -94.71,
   "yoy_12m": 57.18,
   "yoy_3m": 57.56
  },
  "2022-06": {
   "mom": 1104.5,
   "revenue": 250150.0,
   "yoy": -25.89,
   "yoy_12m": 60.7,
   "yoy_3m": -72.04
  },
  "2022-07": {
   "mom": -47.47,
   "revenue": 131397.0,
   "yoy": -77.4,
   "yoy_12m": 54.96,
   "yoy_3m": -66.0
  },
  "2022-08": {
   "mom": 95.6,
   "revenue": 257013.0,
   "yoy": 0.25,
   "yoy_12m": 59.72,
   "yoy_3m": -34.35
  },
  "2022-09": {
   "mom": -20.81,
   "revenue": 203539.0,
   "yoy": -37.93,
   "yoy_12m": 64.41,
   "yoy_3m": -38.36
  },
  "2022-10": {
   "mom": -4.2,
   "revenue": 194992.0,
   "yoy": -25.4,
   "yoy_12m": 67.42,
   "yoy_3m": -21.03
  },
  "2022-11": {
   "mom": -2.61,
   "revenue": 189912.0,
   "yoy": -45.76,
   "yoy_12m": 66.16,
   "yoy_3m": -36.36
  },
  "2022-12": {
   "mom": 821.25,
   "revenue": 1749570.0,
   "yoy": 310.93,
   "yoy_12m": 95.62,
   "yoy_3m": 79.92
  },
  "2023-01": {
   "mom": 85.1,
   "revenue": 3238434.0,
   "yoy": 546.84,
   "yoy_12m": 140.05,
   "yoy_3m": 270.67
  },
  "2023-02": {
   "mom": -93.76,
   "revenue": 202222.0,
   "yoy": -93.07,
   "yoy_12m": 60.44,
   "yoy_3m": 254.9
  },
  "2023-03": {
   "mom": 0.41,
   "revenue": 203043.0,
   "yoy": -92.7,
   "yoy_12m": 22.47,
   "yoy_3m": 120.36
  },
  "2023-04": {
   "mom": 32.34,
   "revenue": 268716.0,
   "yoy": 1035.4,
   "yoy_12m": 116.71,
   "yoy_3m": 283.21
  },
  "2023-05": {
   "mom": -22.28,
   "revenue": 208853.0,
   "yoy": 905.65,
   "yoy_12m": 200.08,
   "yoy_3m": 616.12
  },
  "2023-06": {
   "mom": -5.8,
   "revenue": 196734.0,
   "yoy": -21.35,
   "yoy_12m": 200.46,
   "yoy_3m": 639.9
  },
  "2023-07": {
   "mom": -8.64,
   "revenue": 179730.0,
   "yoy": 36.78,
   "yoy_12m": 209.97,
   "yoy_3m": 307.03
  },
  "2023-08": {
   "mom": 1397.99,
   "revenue": 2692346.0,
   "yoy": 947.55,
   "yoy_12m": 288.91,
   "yoy_3m": 320.99
  },
  "2023-09": {
   "mom": -88.73,
   "revenue": 303360.0,
   "yoy": 49.04,
   "yoy_12m": 296.16,
   "yoy_3m": 344.46
  },
  "2023-10": {
   "mom": -30.04,
   "revenue": 212228.0,
   "yoy": 8.84,
   "yoy_12m": 299.01,
   "yoy_3m": 335.14
  },
  "2023-11": {
   "mom": 10.77,
   "revenue": 235088.0,
   "yoy": 23.79,
   "yoy_12m": 304.81,
   "yoy_3m": 27.22
  },
  "2023-12": {
   "mom": 1525.94,
   "revenue": 3822382.0,
   "yoy": 118.48,
   "yoy_12m": 288.77,
   "yoy_3m": 50.37
  },
  "2024-01": {
   "mom": -3.04,
   "revenue": 3706164.0,
   "yoy": 14.44,
   "yoy_12m": 244.4,
   "yoy_3m": 52.24
  },
  "2024-02": {
   "mom": -93.84,
   "revenue": 228119.0,
   "yoy": 12.81,
   "yoy_12m": 253.23,
   "yoy_3m": 48.58
  },
  "2024-03": {
   "mom": -0.04,
   "revenue": 228019.0,
   "yoy": 12.3,
   "yoy_12m": 261.98,
   "yoy_3m": 13.18
  },
  "2024-04": {
   "mom": 12.28,
   "revenue": 256009.0,
   "yoy": -4.73,
   "yoy_12m": 175.3,
   "yoy_3m": 6.79
  },
  "2024-05": {
   "mom": -4.41,
   "revenue": 244717.0,
   "yoy": 17.17,
   "yoy_12m": 101.26,
   "yoy_3m": 8.25
  },
  "2024-06": {
   "mom": -8.1,
   "revenue": 224888.0,
   "yoy": 14.31,
   "yoy_12m": 104.23,
   "yoy_3m": 8.92
  },
  "2024-07": {
   "mom": 667.6,
   "revenue": 1726231.0,
   "yoy": 860.46,
   "yoy_12m": 172.87,
   "yoy_3m": 297.31
  },
  "2024-08": {
   "mom": -63.21,
   "revenue": 635029.0,
   "yoy": -76.41,
   "yoy_12m": 87.54,
   "yoy_3m": 266.12
  },
  "2024-09": {
   "mom": -47.59,
   "revenue": 332798.0,
   "yoy": 9.7,
   "yoy_12m": 84.26,
   "yoy_3m": 264.58
  },
  "2024-10": {
   "mom": 9.65,
   "revenue": 364898.0,
   "yoy": 71.94,
   "yoy_12m": 89.52,
   "yoy_3m": 1.74
  },
  "2024-11": {
   "mom": -18.6,
   "revenue": 297029.0,
   "yoy": 26.35,
   "yoy_12m": 89.73,
   "yoy_3m": 36.0
  },
  "2024-12": {
   "mom": -18.09,
   "revenue": 243294.0,
   "yoy": -93.64,
   "yoy_12m": 72.06,
   "yoy_3m": 1.55
  },
  "2025-01": {
   "mom": 3.76,
   "revenue": 252452.0,
   "yoy": -93.19,
   "yoy_12m": 63.09,
   "yoy_3m": -53.49
  },
  "2025-02": {
   "mom": 1.64,
   "revenue": 256581.0,
   "yoy": 12.48,
   "yoy_12m": 63.06,
   "yoy_3m": -58.12
  },
  "2025-03": {
   "mom": 19.35,
   "revenue": 306241.0,
   "yoy": 34.31,
   "yoy_12m": 64.9,
   "yoy_3m": -15.47
  },
  "2025-04": {
   "mom": -27.33,
   "revenue": 222554.0,
   "yoy": -13.07,
   "yoy_12m": 64.2,
   "yoy_3m": 11.24
  },
  "2025-05": {
   "mom": 41.93,
   "revenue": 315881.0,
   "yoy": 29.08,
   "yoy_12m": 65.19,
   "yoy_3m": 16.77
  },
  "2025-06": {
   "mom": -28.8,
   "revenue": 224904.0,
   "yoy": 0.01,
   "yoy_12m": 64.0,
   "yoy_3m": 5.34
  },
  "2025-07": {
   "mom": 62.05,
   "revenue": 364455.0,
   "yoy": -78.89,
   "yoy_12m": -14.28,
   "yoy_3m": -16.6
  },
  "2025-08": {
   "mom": -33.51,
   "revenue": 242327.0,
   "yoy": -61.84,
   "yoy_12m": -13.06,
   "yoy_3m": -46.91
  },
  "2025-09": {
   "mom": 2.51,
   "revenue": 248408.0,
   "yoy": -25.36,
   "yoy_12m": -15.98,
   "yoy_3m": -55.36
  },
  "2025-10": {
   "mom": 8.3,
   "revenue": 269023.0,
   "yoy": -26.27,
   "yoy_12m": -24.17,
   "yoy_3m": -37.82
  },
  "2025-11": {
   "mom": -6.19,
   "revenue": 252368.0,
   "yoy": -15.04,
   "yoy_12m": -27.62,
   "yoy_3m": -22.22
  },
  "2025-12": {
   "mom": 1051.01,
   "revenue": 2904783.0,
   "yoy": 1093.94,
   "yoy_12m": 71.35,
   "yoy_3m": 350.88
  },
  "2026-01": {
   "mom": -49.49,
   "revenue": 1467097.0,
   "yoy": 481.14,
   "yoy_12m": 119.21,
   "yoy_3m": 520.01
  },
  "2026-02": {
   "mom": -77.46,
   "revenue": 330662.0,
   "yoy": 28.87,
   "yoy_12m": 120.57,
   "yoy_3m": 534.65
  },
  "2026-03": {
   "mom": -21.51,
   "revenue": 259546.0,
   "yoy": -15.25,
   "yoy_12m": 116.44,
   "yoy_3m": 164.92
  },
  "2026-04": {
   "mom": 123.67,
   "revenue": 580523.0,
   "yoy": 160.85,
   "yoy_12m": 130.94,
   "yoy_3m": 58.16
  },
  "2026-05": {
   "mom": 27.1,
   "revenue": 737837,
   "yoy": 133.58,
   "yoy_12m": 139.65,
   "yoy_3m": 93.06
  },
  "2026-06": {
   "mom": 20.35,
   "revenue": 888017,
   "yoy": 294.84,
   "yoy_12m": 164.21,
   "yoy_3m": 196.42
  }
 },
 "name": "鼎固-KY",
 "price_return_1y": 56.55,
 "quarterly": {
  "2015Q1": {
   "cogs": 1913538.0,
   "current_assets": 46428762.0,
   "current_liabilities": 13120719.0,
   "current_ratio": 353.86,
   "debt_ratio": 52.25,
   "eps": 0.33,
   "equity": 56370700.0,
   "equity_parent": 53576272.0,
   "gross_margin": 43.17,
   "gross_profit": 1453597.0,
   "net_income": 592312.0,
   "net_margin": 17.59,
   "operating_expenses": 186193.0,
   "operating_income": 1267404.0,
   "operating_margin": 37.64,
   "pretax_income": 1078536.0,
   "revenue": 3367135.0,
   "roa_q": 0.5,
   "roe_q": 1.05,
   "total_assets": 118056872.0,
   "total_liabilities": 61686172.0
  },
  "2015Q2": {
   "cogs": 1052986.0,
   "current_assets": 48713930.0,
   "current_liabilities": 14697815.0,
   "current_ratio": 331.44,
   "debt_ratio": 53.5,
   "eps": 0.46,
   "equity": 56130126.0,
   "equity_parent": 53298594.0,
   "gross_margin": 49.1,
   "gross_profit": 1015791.0,
   "net_income": 872333.0,
   "net_margin": 42.17,
   "operating_expenses": 187537.0,
   "operating_income": 2181298.0,
   "operating_margin": 105.44,
   "pretax_income": 1982971.0,
   "revenue": 2068777.0,
   "roa_q": 0.72,
   "roe_q": 1.55,
   "total_assets": 120717267.0,
   "total_liabilities": 64587141.0
  },
  "2015Q3": {
   "cogs": 2680753.0,
   "current_assets": 50387186.0,
   "current_liabilities": 14849893.0,
   "current_ratio": 339.31,
   "debt_ratio": 53.55,
   "eps": 0.45,
   "equity": 58608048.0,
   "equity_parent": 55635786.0,
   "gross_margin": 42.64,
   "gross_profit": 1992810.0,
   "net_income": 799213.0,
   "net_margin": 17.1,
   "operating_expenses": 251024.0,
   "operating_income": 1741786.0,
   "operating_margin": 37.27,
   "pretax_income": 1565967.0,
   "revenue": 4673563.0,
   "roa_q": 0.63,
   "roe_q": 1.36,
   "total_assets": 126170863.0,
   "total_liabilities": 67562815.0
  },
  "2015Q4": {
   "cogs": 1247145.0,
   "current_assets": 48578073.0,
   "current_liabilities": 15281175.0,
   "current_ratio": 317.89,
   "debt_ratio": 53.35,
   "eps": 0.77,
   "eps_ttm": 2.01,
   "equity": 57637056.0,
   "equity_parent": 54676389.0,
   "gross_margin": 53.39,
   "gross_profit": 1428583.0,
   "net_income": 1426263.0,
   "net_income_ttm": 3690121.0,
   "net_margin": 53.3,
   "operating_expenses": 233663.0,
   "operating_income": 3116879.0,
   "operating_margin": 116.49,
   "pretax_income": 2954463.0,
   "revenue": 2675728.0,
   "revenue_ttm": 12785203.0,
   "roa_q": 1.15,
   "roa_ttm": 2.99,
   "roe_q": 2.47,
   "roe_ttm": 6.4,
   "total_assets": 123548588.0,
   "total_liabilities": 65911532.0
  },
  "2016Q1": {
   "cogs": 896882.0,
   "current_assets": 46989183.0,
   "current_liabilities": 9800981.0,
   "current_ratio": 479.43,
   "debt_ratio": 52.42,
   "eps": 0.2,
   "eps_ttm": 1.88,
   "eps_yoy": -39.39,
   "equity": 57830526.0,
   "equity_parent": 54858056.0,
   "gross_margin": 57.76,
   "gross_profit": 1226575.0,
   "net_income": 377655.0,
   "net_income_ttm": 3475464.0,
   "net_income_yoy": -36.24,
   "net_margin": 17.78,
   "operating_expenses": 152471.0,
   "operating_income": 1074104.0,
   "operating_income_yoy": -15.25,
   "operating_margin": 50.58,
   "pretax_income": 736849.0,
   "revenue": 2123457.0,
   "revenue_ttm": 11541525.0,
   "revenue_yoy": -36.94,
   "roa_q": 0.31,
   "roa_ttm": 2.86,
   "roe_q": 0.65,
   "roe_ttm": 6.01,
   "total_assets": 121532665.0,
   "total_liabilities": 63702139.0
  },
  "2016Q2": {
   "cogs": 556881.0,
   "current_assets": 45518740.0,
   "current_liabilities": 9783905.0,
   "current_ratio": 465.24,
   "debt_ratio": 53.03,
   "eps": 0.56,
   "eps_ttm": 1.98,
   "eps_yoy": 21.74,
   "equity": 56225710.0,
   "equity_parent": 53318215.0,
   "gross_margin": 62.8,
   "gross_profit": 939981.0,
   "net_income": 987424.0,
   "net_income_ttm": 3590555.0,
   "net_income_yoy": 13.19,
   "net_margin": 65.97,
   "operating_expenses": 138280.0,
   "operating_income": 2300435.0,
   "operating_income_yoy": 5.46,
   "operating_income_yoy_accel": 20.71,
   "operating_margin": 153.68,
   "pretax_income": 2184069.0,
   "revenue": 1496862.0,
   "revenue_ttm": 10969610.0,
   "revenue_yoy": -27.65,
   "revenue_yoy_accel": 9.29,
   "roa_q": 0.82,
   "roa_ttm": 3.0,
   "roe_q": 1.76,
   "roe_ttm": 6.39,
   "total_assets": 119712946.0,
   "total_liabilities": 63487236.0
  },
  "2016Q3": {
   "cogs": 452866.0,
   "current_assets": 44849260.0,
   "current_liabilities": 8841020.0,
   "current_ratio": 507.29,
   "debt_ratio": 53.27,
   "eps": 0.14,
   "eps_ttm": 1.67,
   "eps_yoy": -68.89,
   "equity": 54615221.0,
   "equity_parent": 51775411.0,
   "gross_margin": 64.36,
   "gross_profit": 817729.0,
   "net_income": 271659.0,
   "net_income_ttm": 3063001.0,
   "net_income_yoy": -66.01,
   "net_margin": 21.38,
   "operating_expenses": 110260.0,
   "operating_income": 707469.0,
   "operating_income_yoy": -59.38,
   "operating_income_yoy_accel": -64.84,
   "operating_margin": 55.68,
   "pretax_income": 486860.0,
   "revenue": 1270595.0,
   "revenue_ttm": 7566642.0,
   "revenue_yoy": -72.81,
   "revenue_yoy_accel": -45.16,
   "roa_q": 0.23,
   "roa_ttm": 2.62,
   "roe_q": 0.5,
   "roe_ttm": 5.61,
   "total_assets": 116871583.0,
   "total_liabilities": 62256362.0
  },
  "2016Q4": {
   "cogs": 1349802.0,
   "eps": 0.47,
   "eps_ttm": 1.37,
   "eps_yoy": -38.96,
   "gross_margin": 47.31,
   "gross_profit": 1211974.0,
   "net_income": 803044.0,
   "net_income_ttm": 2439782.0,
   "net_income_yoy": -43.7,
   "net_margin": 31.35,
   "operating_expenses": 180883.0,
   "operating_income": 902325.0,
   "operating_income_yoy": -71.05,
   "operating_income_yoy_accel": -11.67,
   "operating_margin": 35.22,
   "pretax_income": 1085104.0,
   "revenue": 2561776.0,
   "revenue_ttm": 7452690.0,
   "revenue_yoy": -4.26,
   "revenue_yoy_accel": 68.55
  },
  "2017Q1": {
   "cogs": 455777.0,
   "current_assets": 41676601.0,
   "current_liabilities": 8427985.0,
   "current_ratio": 494.5,
   "debt_ratio": 52.34,
   "eps": 0.13,
   "eps_ttm": 1.3,
   "eps_yoy": -35.0,
   "equity": 51703961.0,
   "equity_parent": 49035090.0,
   "gross_margin": 65.54,
   "gross_profit": 867007.0,
   "net_income": 241331.0,
   "net_income_ttm": 2303458.0,
   "net_income_yoy": -36.1,
   "net_margin": 18.24,
   "operating_expenses": 121208.0,
   "operating_income": 745799.0,
   "operating_income_yoy": -30.57,
   "operating_income_yoy_accel": 40.48,
   "operating_margin": 56.38,
   "pretax_income": 498930.0,
   "revenue": 1322784.0,
   "revenue_ttm": 6652017.0,
   "revenue_yoy": -37.71,
   "revenue_yoy_accel": -33.45,
   "roa_q": 0.22,
   "roa_ttm": 2.12,
   "roe_q": 0.47,
   "roe_ttm": 4.46,
   "total_assets": 108481490.0,
   "total_liabilities": 56777529.0
  },
  "2017Q2": {
   "cogs": 365934.0,
   "current_assets": 40732234.0,
   "current_liabilities": 9527845.0,
   "current_ratio": 427.51,
   "debt_ratio": 53.08,
   "eps": -0.12,
   "eps_ttm": 0.62,
   "eps_yoy": -121.43,
   "equity": 52177937.0,
   "equity_parent": 49438927.0,
   "gross_margin": 67.48,
   "gross_profit": 759282.0,
   "net_income": -192281.0,
   "net_income_ttm": 1123753.0,
   "net_income_yoy": -119.47,
   "net_margin": -17.09,
   "operating_expenses": 111361.0,
   "operating_income": 802361.0,
   "operating_income_yoy": -65.12,
   "operating_income_yoy_accel": -34.55,
   "operating_margin": 71.31,
   "pretax_income": 159045.0,
   "revenue": 1125216.0,
   "revenue_ttm": 6280371.0,
   "revenue_yoy": -24.83,
   "revenue_yoy_accel": 12.88,
   "roa_q": -0.17,
   "roa_ttm": 1.01,
   "roe_q": -0.37,
   "roe_ttm": 2.15,
   "total_assets": 111202844.0,
   "total_liabilities": 59024907.0
  },
  "2017Q3": {
   "cogs": 460867.0,
   "eps": 0.06,
   "eps_ttm": 0.54,
   "eps_yoy": -57.14,
   "gross_margin": 65.2,
   "gross_profit": 863545.0,
   "net_income": 144291.0,
   "net_income_ttm": 996385.0,
   "net_income_yoy": -46.89,
   "net_margin": 10.89,
   "operating_expenses": 110974.0,
   "operating_income": 752571.0,
   "operating_income_yoy": 6.38,
   "operating_income_yoy_accel": 71.5,
   "operating_margin": 56.82,
   "pretax_income": 353031.0,
   "revenue": 1324412.0,
   "revenue_ttm": 6334188.0,
   "revenue_yoy": 4.24,
   "revenue_yoy_accel": 29.07
  },
  "2017Q4": {
   "cogs": 542429.0,
   "eps": 0.01,
   "eps_ttm": 0.08,
   "eps_yoy": -97.87,
   "gross_margin": 56.71,
   "gross_profit": 710708.0,
   "net_income": -3277.0,
   "net_income_ttm": 190064.0,
   "net_income_yoy": -100.41,
   "net_margin": -0.26,
   "operating_expenses": 124244.0,
   "operating_income": 339795.0,
   "operating_income_yoy": -62.34,
   "operating_income_yoy_accel": -68.72,
   "operating_margin": 27.12,
   "pretax_income": 119367.0,
   "revenue": 1253137.0,
   "revenue_ttm": 5025549.0,
   "revenue_yoy": -51.08,
   "revenue_yoy_accel": -55.32
  },
  "2018Q1": {
   "cogs": 387940.0,
   "eps": -0.02,
   "eps_ttm": -0.07,
   "eps_yoy": -115.38,
   "gross_margin": 68.09,
   "gross_profit": 827931.0,
   "net_income": -13218.0,
   "net_income_ttm": -64485.0,
   "net_income_yoy": -105.48,
   "net_margin": -1.09,
   "operating_expenses": 86040.0,
   "operating_income": 741891.0,
   "operating_income_yoy": -0.52,
   "operating_income_yoy_accel": 61.82,
   "operating_margin": 61.02,
   "pretax_income": 191691.0,
   "revenue": 1215871.0,
   "revenue_ttm": 4918636.0,
   "revenue_yoy": -8.08,
   "revenue_yoy_accel": 43.0
  },
  "2018Q2": {
   "cogs": 371484.0,
   "eps": 0.28,
   "eps_ttm": 0.33,
   "eps_yoy": 333.33,
   "gross_margin": 69.73,
   "gross_profit": 855600.0,
   "net_income": 457119.0,
   "net_income_ttm": 584915.0,
   "net_income_yoy": 337.73,
   "net_margin": 37.25,
   "operating_expenses": 126854.0,
   "operating_income": 277834.0,
   "operating_income_yoy": -65.37,
   "operating_income_yoy_accel": -64.85,
   "operating_margin": 22.64,
   "pretax_income": 342267.0,
   "revenue": 1227084.0,
   "revenue_ttm": 5020504.0,
   "revenue_yoy": 9.05,
   "revenue_yoy_accel": 17.13
  },
  "2018Q3": {
   "cogs": 392348.0,
   "eps": 0.08,
   "eps_ttm": 0.35,
   "eps_yoy": 33.33,
   "gross_margin": 65.59,
   "gross_profit": 747814.0,
   "net_income": 163482.0,
   "net_income_ttm": 604106.0,
   "net_income_yoy": 13.3,
   "net_margin": 14.34,
   "operating_expenses": 144176.0,
   "operating_income": 603638.0,
   "operating_income_yoy": -19.79,
   "operating_income_yoy_accel": 45.58,
   "operating_margin": 52.94,
   "pretax_income": 351069.0,
   "revenue": 1140162.0,
   "revenue_ttm": 4836254.0,
   "revenue_yoy": -13.91,
   "revenue_yoy_accel": -22.96
  },
  "2018Q4": {
   "cogs": 1778279.0,
   "current_assets": 71656247.0,
   "current_liabilities": 18758836.0,
   "current_ratio": 381.99,
   "debt_ratio": 55.87,
   "eps": 0.6,
   "eps_ttm": 0.94,
   "eps_yoy": 5900.0,
   "equity": 52523680.0,
   "equity_parent": 50016763.0,
   "gross_margin": 46.85,
   "gross_profit": 1567326.0,
   "net_income": 1025776.0,
   "net_income_ttm": 1633159.0,
   "net_income_yoy": 31402.29,
   "net_margin": 30.66,
   "operating_expenses": 32570.0,
   "operating_income": 2549395.0,
   "operating_income_yoy": 650.27,
   "operating_income_yoy_accel": 670.06,
   "operating_margin": 76.2,
   "pretax_income": 2291694.0,
   "revenue": 3345605.0,
   "revenue_ttm": 6928722.0,
   "revenue_yoy": 166.98,
   "revenue_yoy_accel": 180.89,
   "roa_q": 0.86,
   "roa_ttm": 1.37,
   "roe_q": 1.95,
   "roe_ttm": 3.11,
   "total_assets": 119024757.0,
   "total_liabilities": 66501077.0
  },
  "2019Q1": {
   "cogs": 410236.0,
   "eps": 4.74,
   "eps_ttm": 5.7,
   "eps_yoy": 23800.0,
   "gross_margin": 64.63,
   "gross_profit": 749576.0,
   "net_income": 8258952.0,
   "net_income_ttm": 9905329.0,
   "net_income_yoy": 62582.61,
   "net_margin": 712.09,
   "operating_expenses": 494454.0,
   "operating_income": 255122.0,
   "operating_income_yoy": -65.61,
   "operating_income_yoy_accel": -715.88,
   "operating_margin": 22.0,
   "pretax_income": 571275.0,
   "revenue": 1159812.0,
   "revenue_ttm": 6872663.0,
   "revenue_yoy": -4.61,
   "revenue_yoy_accel": -171.59
  },
  "2019Q2": {
   "cogs": 1322278.0,
   "eps": 0.25,
   "eps_ttm": 5.67,
   "eps_yoy": -10.71,
   "gross_margin": 39.06,
   "gross_profit": 847619.0,
   "net_income": 441265.0,
   "net_income_ttm": 9889475.0,
   "net_income_yoy": -3.47,
   "net_margin": 20.34,
   "operating_expenses": 136702.0,
   "operating_income": 701797.0,
   "operating_income_yoy": 152.6,
   "operating_income_yoy_accel": 218.21,
   "operating_margin": 32.34,
   "pretax_income": 660668.0,
   "revenue": 2169897.0,
   "revenue_ttm": 7815476.0,
   "revenue_yoy": 76.83,
   "revenue_yoy_accel": 81.44
  },
  "2019Q3": {
   "cogs": 437387.0,
   "current_assets": 56908566.0,
   "current_liabilities": 9790237.0,
   "current_ratio": 581.28,
   "debt_ratio": 53.34,
   "eps": 0.2,
   "eps_ttm": 5.79,
   "eps_yoy": 150.0,
   "equity": 55861183.0,
   "equity_parent": 55783534.0,
   "gross_margin": 56.98,
   "gross_profit": 579409.0,
   "net_income": 356269.0,
   "net_income_ttm": 10082262.0,
   "net_income_yoy": 117.93,
   "net_margin": 35.04,
   "operating_expenses": 106431.0,
   "operating_income": 472978.0,
   "operating_income_yoy": -21.65,
   "operating_income_yoy_accel": -174.25,
   "operating_margin": 46.52,
   "pretax_income": 515571.0,
   "revenue": 1016796.0,
   "revenue_ttm": 7692110.0,
   "revenue_yoy": -10.82,
   "revenue_yoy_accel": -87.65,
   "roa_q": 0.3,
   "roa_ttm": 8.42,
   "roe_q": 0.64,
   "roe_ttm": 18.05,
   "total_assets": 119719079.0,
   "total_liabilities": 63857896.0
  },
  "2019Q4": {
   "cogs": 715565.0,
   "current_assets": 59079536.0,
   "current_liabilities": 15014025.0,
   "current_ratio": 393.5,
   "debt_ratio": 55.64,
   "eps": -0.48,
   "eps_ttm": 4.71,
   "eps_yoy": -180.0,
   "equity": 54808574.0,
   "equity_parent": 54731787.0,
   "gross_margin": 48.55,
   "gross_profit": 675136.0,
   "net_income": -842845.0,
   "net_income_ttm": 8213641.0,
   "net_income_yoy": -182.17,
   "net_margin": -60.61,
   "operating_expenses": 34497.0,
   "operating_income": -2079128.0,
   "operating_income_yoy": -181.55,
   "operating_income_yoy_accel": -159.9,
   "operating_margin": -149.5,
   "pretax_income": -2105603.0,
   "revenue": 1390701.0,
   "revenue_ttm": 5737206.0,
   "revenue_yoy": -58.43,
   "revenue_yoy_accel": -47.61,
   "roa_q": -0.68,
   "roa_ttm": 6.65,
   "roe_q": -1.54,
   "roe_ttm": 14.99,
   "total_assets": 123547400.0,
   "total_liabilities": 68738826.0
  },
  "2020Q1": {
   "cogs": 530319.0,
   "current_assets": 60595599.0,
   "current_liabilities": 19219354.0,
   "current_ratio": 315.28,
   "debt_ratio": 58.67,
   "eps": -0.24,
   "eps_ttm": -0.27,
   "eps_yoy": -105.06,
   "equity": 51647372.0,
   "equity_parent": 51571491.0,
   "gross_margin": 54.28,
   "gross_profit": 629562.0,
   "net_income": -423769.0,
   "net_income_ttm": -469080.0,
   "net_income_yoy": -105.13,
   "net_margin": -36.54,
   "operating_expenses": 87015.0,
   "operating_income": 542547.0,
   "operating_income_yoy": 112.66,
   "operating_income_yoy_accel": 294.21,
   "operating_margin": 46.78,
   "pretax_income": -203874.0,
   "revenue": 1159881.0,
   "revenue_ttm": 5737275.0,
   "revenue_yoy": 0.01,
   "revenue_yoy_accel": 58.44,
   "roa_q": -0.34,
   "roa_ttm": -0.38,
   "roe_q": -0.82,
   "roe_ttm": -0.91,
   "total_assets": 124965365.0,
   "total_liabilities": 73317993.0
  },
  "2020Q2": {
   "cogs": 2323443.0,
   "current_assets": 60722669.0,
   "current_liabilities": 21834306.0,
   "current_ratio": 278.11,
   "debt_ratio": 60.73,
   "eps": -0.01,
   "eps_ttm": -0.53,
   "eps_yoy": -104.0,
   "equity": 48764244.0,
   "equity_parent": 48689520.0,
   "gross_margin": 33.37,
   "gross_profit": 1163613.0,
   "net_income": -24635.0,
   "net_income_ttm": -934980.0,
   "net_income_yoy": -105.58,
   "net_margin": -0.71,
   "operating_expenses": 173420.0,
   "operating_income": 598209.0,
   "operating_income_yoy": -14.76,
   "operating_income_yoy_accel": -127.42,
   "operating_margin": 17.16,
   "pretax_income": 230854.0,
   "revenue": 3487056.0,
   "revenue_ttm": 7054434.0,
   "revenue_yoy": 60.7,
   "revenue_yoy_accel": 60.69,
   "roa_q": -0.02,
   "roa_ttm": -0.75,
   "roe_q": -0.05,
   "roe_ttm": -1.92,
   "total_assets": 124186381.0,
   "total_liabilities": 75422137.0
  },
  "2020Q3": {
   "cogs": 3836167.0,
   "current_assets": 59169952.0,
   "current_liabilities": 19432641.0,
   "current_ratio": 304.49,
   "debt_ratio": 57.62,
   "eps": 0.65,
   "eps_ttm": -0.08,
   "eps_yoy": 225.0,
   "equity": 51554950.0,
   "equity_parent": 51478838.0,
   "gross_margin": 43.71,
   "gross_profit": 2979207.0,
   "net_income": 1129598.0,
   "net_income_ttm": -161651.0,
   "net_income_yoy": 217.06,
   "net_margin": 16.57,
   "operating_expenses": 283747.0,
   "operating_income": 1856280.0,
   "operating_income_yoy": 292.47,
   "operating_income_yoy_accel": 307.23,
   "operating_margin": 27.24,
   "pretax_income": 2001169.0,
   "revenue": 6815374.0,
   "revenue_ttm": 12853012.0,
   "revenue_yoy": 570.28,
   "revenue_yoy_accel": 509.58,
   "roa_q": 0.93,
   "roa_ttm": -0.13,
   "roe_q": 2.19,
   "roe_ttm": -0.31,
   "total_assets": 121639522.0,
   "total_liabilities": 70084572.0
  },
  "2020Q4": {
   "cogs": 1207484.0,
   "current_assets": 53860296.0,
   "current_liabilities": 7992274.0,
   "current_ratio": 673.9,
   "debt_ratio": 53.52,
   "eps": 0.29,
   "eps_ttm": 0.69,
   "eps_yoy": 160.42,
   "equity": 54151689.0,
   "equity_parent": 54073659.0,
   "gross_margin": 38.32,
   "gross_profit": 750121.0,
   "net_income": 496161.0,
   "net_income_ttm": 1177355.0,
   "net_income_yoy": 158.87,
   "net_margin": 25.35,
   "operating_expenses": 219210.0,
   "operating_income": 301849.0,
   "operating_income_yoy": 114.52,
   "operating_income_yoy_accel": -177.95,
   "operating_margin": 15.42,
   "pretax_income": 667446.0,
   "revenue": 1957605.0,
   "revenue_ttm": 13419916.0,
   "revenue_yoy": 40.76,
   "revenue_yoy_accel": -529.52,
   "roa_q": 0.43,
   "roa_ttm": 1.01,
   "roe_q": 0.92,
   "roe_ttm": 2.17,
   "total_assets": 116503422.0,
   "total_liabilities": 62351733.0
  },
  "2021Q1": {
   "cogs": 572400.0,
   "current_assets": 57840937.0,
   "current_liabilities": 29568126.0,
   "current_ratio": 195.62,
   "debt_ratio": 54.04,
   "eps": 0.44,
   "eps_ttm": 1.37,
   "eps_yoy": 283.33,
   "equity": 54383533.0,
   "equity_parent": 54306097.0,
   "gross_margin": 57.45,
   "gross_profit": 772852.0,
   "net_income": 768508.0,
   "net_income_ttm": 2369632.0,
   "net_income_yoy": 281.35,
   "net_margin": 57.13,
   "operating_expenses": 195643.0,
   "operating_income": 577209.0,
   "operating_income_yoy": 6.39,
   "operating_income_yoy_accel": -108.13,
   "operating_margin": 42.91,
   "pretax_income": 1049522.0,
   "revenue": 1345252.0,
   "revenue_ttm": 13605287.0,
   "revenue_yoy": 15.98,
   "revenue_yoy_accel": -24.78,
   "roa_q": 0.65,
   "roa_ttm": 2.0,
   "roe_q": 1.41,
   "roe_ttm": 4.36,
   "total_assets": 118318880.0,
   "total_liabilities": 63935347.0
  },
  "2021Q2": {
   "cogs": 539259.0,
   "current_assets": 62210958.0,
   "current_liabilities": 33740401.0,
   "current_ratio": 184.38,
   "debt_ratio": 54.88,
   "eps": 0.33,
   "eps_ttm": 1.71,
   "eps_yoy": 3400.0,
   "equity": 52403048.0,
   "equity_parent": 52326237.0,
   "gross_margin": 57.06,
   "gross_profit": 716691.0,
   "net_income": 565832.0,
   "net_income_ttm": 2960099.0,
   "net_income_yoy": 2396.86,
   "net_margin": 45.05,
   "operating_expenses": 166535.0,
   "operating_income": 489207.0,
   "operating_income_yoy": -18.22,
   "operating_income_yoy_accel": -24.61,
   "operating_margin": 38.95,
   "pretax_income": 745780.0,
   "revenue": 1255950.0,
   "revenue_ttm": 11374181.0,
   "revenue_yoy": -63.98,
   "revenue_yoy_accel": -79.96,
   "roa_q": 0.49,
   "roa_ttm": 2.55,
   "roe_q": 1.08,
   "roe_ttm": 5.65,
   "total_assets": 116139955.0,
   "total_liabilities": 63736907.0
  },
  "2021Q3": {
   "cogs": 514029.0,
   "current_assets": 64987499.0,
   "current_liabilities": 33074225.0,
   "current_ratio": 196.49,
   "debt_ratio": 54.67,
   "eps": -0.08,
   "eps_ttm": 0.98,
   "eps_yoy": -112.31,
   "equity": 52046163.0,
   "equity_parent": 51969434.0,
   "gross_margin": 55.84,
   "gross_profit": 649938.0,
   "net_income": -139013.0,
   "net_income_ttm": 1691488.0,
   "net_income_yoy": -112.31,
   "net_margin": -11.94,
   "operating_expenses": 157080.0,
   "operating_income": 492858.0,
   "operating_income_yoy": -73.45,
   "operating_income_yoy_accel": -55.23,
   "operating_margin": 42.34,
   "pretax_income": 78293.0,
   "revenue": 1163967.0,
   "revenue_ttm": 5722774.0,
   "revenue_yoy": -82.92,
   "revenue_yoy_accel": -18.94,
   "roa_q": -0.12,
   "roa_ttm": 1.47,
   "roe_q": -0.27,
   "roe_ttm": 3.25,
   "total_assets": 114811222.0,
   "total_liabilities": 62765059.0
  },
  "2021Q4": {
   "cogs": 510202.0,
   "current_assets": 63163245.0,
   "current_liabilities": 31372226.0,
   "current_ratio": 201.33,
   "debt_ratio": 52.56,
   "eps": -0.02,
   "eps_ttm": 0.67,
   "eps_yoy": -106.9,
   "equity": 52695411.0,
   "equity_parent": 52617989.0,
   "gross_margin": 50.85,
   "gross_profit": 527817.0,
   "net_income": -24313.0,
   "net_income_ttm": 1171014.0,
   "net_income_yoy": -104.9,
   "net_margin": -2.34,
   "operating_expenses": 135923.0,
   "operating_income": 265848.0,
   "operating_income_yoy": -11.93,
   "operating_income_yoy_accel": 61.52,
   "operating_margin": 25.61,
   "pretax_income": 90955.0,
   "revenue": 1038019.0,
   "revenue_ttm": 4803188.0,
   "revenue_yoy": -46.98,
   "revenue_yoy_accel": 35.94,
   "roa_q": -0.02,
   "roa_ttm": 1.05,
   "roe_q": -0.05,
   "roe_ttm": 2.22,
   "total_assets": 111073696.0,
   "total_liabilities": 58378285.0
  },
  "2022Q1": {
   "cogs": 2345080.0,
   "current_assets": 62953471.0,
   "current_liabilities": 11318096.0,
   "current_ratio": 556.22,
   "debt_ratio": 50.11,
   "eps": 0.83,
   "eps_ttm": 1.06,
   "eps_yoy": 88.64,
   "equity": 55918029.0,
   "equity_parent": 55837715.0,
   "gross_margin": 61.98,
   "gross_profit": 3823353.0,
   "net_income": 1440954.0,
   "net_income_ttm": 1843460.0,
   "net_income_yoy": 87.5,
   "net_margin": 23.36,
   "operating_expenses": 321623.0,
   "operating_income": 3501730.0,
   "operating_income_yoy": 506.67,
   "operating_income_yoy_accel": 518.6,
   "operating_margin": 56.77,
   "pretax_income": 3500393.0,
   "revenue": 6168433.0,
   "revenue_ttm": 9626369.0,
   "revenue_yoy": 358.53,
   "revenue_yoy_accel": 405.51,
   "roa_q": 1.29,
   "roa_ttm": 1.64,
   "roe_q": 2.58,
   "roe_ttm": 3.3,
   "total_assets": 112076332.0,
   "total_liabilities": 56158303.0
  },
  "2022Q2": {
   "cogs": 171726.0,
   "current_assets": 60178369.0,
   "current_liabilities": 11000732.0,
   "current_ratio": 547.04,
   "debt_ratio": 51.91,
   "eps": -0.2,
   "eps_ttm": 0.53,
   "eps_yoy": -160.61,
   "equity": 51706704.0,
   "equity_parent": 51627579.0,
   "gross_margin": 46.73,
   "gross_profit": 150668.0,
   "net_income": -349947.0,
   "net_income_ttm": 927681.0,
   "net_income_yoy": -161.85,
   "net_margin": -108.55,
   "operating_expenses": 60575.0,
   "operating_income": -343685.0,
   "operating_income_yoy": -170.25,
   "operating_income_yoy_accel": -676.92,
   "operating_margin": -106.6,
   "pretax_income": -504831.0,
   "revenue": 322394.0,
   "revenue_ttm": 8692813.0,
   "revenue_yoy": -74.33,
   "revenue_yoy_accel": -432.86,
   "roa_q": -0.33,
   "roa_ttm": 0.86,
   "roe_q": -0.68,
   "roe_ttm": 1.79,
   "total_assets": 107522912.0,
   "total_liabilities": 55816208.0
  },
  "2022Q3": {
   "cogs": 294448.0,
   "current_assets": 67804683.0,
   "current_liabilities": 17319211.0,
   "current_ratio": 391.5,
   "debt_ratio": 56.21,
   "eps": -0.24,
   "eps_ttm": 0.37,
   "eps_yoy": -200.0,
   "equity": 50639074.0,
   "equity_parent": 50559344.0,
   "gross_margin": 50.43,
   "gross_profit": 299540.0,
   "net_income": -422745.0,
   "net_income_ttm": 643949.0,
   "net_income_yoy": -204.1,
   "net_margin": -71.17,
   "operating_expenses": 93149.0,
   "operating_income": 206391.0,
   "operating_income_yoy": -58.12,
   "operating_income_yoy_accel": 112.13,
   "operating_margin": 34.75,
   "pretax_income": -354532.0,
   "revenue": 593988.0,
   "revenue_ttm": 8122834.0,
   "revenue_yoy": -48.97,
   "revenue_yoy_accel": 25.36,
   "roa_q": -0.37,
   "roa_ttm": 0.56,
   "roe_q": -0.83,
   "roe_ttm": 1.27,
   "total_assets": 115647809.0,
   "total_liabilities": 65008735.0
  },
  "2022Q4": {
   "cogs": 939685.0,
   "eps": -0.04,
   "eps_ttm": 0.35,
   "eps_yoy": -100.0,
   "gross_margin": 56.02,
   "gross_profit": 1197077.0,
   "net_income": -75453.0,
   "net_income_ttm": 592809.0,
   "net_income_yoy": -210.34,
   "net_margin": -3.53,
   "operating_expenses": 125275.0,
   "operating_income": 71003.0,
   "operating_income_yoy": -73.29,
   "operating_income_yoy_accel": -15.17,
   "operating_margin": 3.32,
   "pretax_income": 96082.0,
   "revenue": 2136762.0,
   "revenue_ttm": 9221577.0,
   "revenue_yoy": 105.85,
   "revenue_yoy_accel": 154.82
  },
  "2023Q1": {
   "cogs": 1723494.0,
   "current_assets": 66793818.0,
   "current_liabilities": 17176101.0,
   "current_ratio": 388.88,
   "debt_ratio": 54.6,
   "eps": 0.22,
   "eps_ttm": -0.26,
   "eps_yoy": -73.49,
   "equity": 51413021.0,
   "equity_parent": 51334038.0,
   "gross_margin": 52.36,
   "gross_profit": 1894594.0,
   "net_income": 376439.0,
   "net_income_ttm": -471706.0,
   "net_income_yoy": -73.88,
   "net_margin": 10.4,
   "operating_expenses": 210899.0,
   "operating_income": 1683695.0,
   "operating_income_yoy": -51.92,
   "operating_income_yoy_accel": 21.37,
   "operating_margin": 46.54,
   "pretax_income": 1625017.0,
   "revenue": 3618088.0,
   "revenue_ttm": 6671232.0,
   "revenue_yoy": -41.35,
   "revenue_yoy_accel": -147.2,
   "roa_q": 0.33,
   "roa_ttm": -0.42,
   "roe_q": 0.73,
   "roe_ttm": -0.92,
   "total_assets": 113239871.0,
   "total_liabilities": 61826850.0
  },
  "2023Q2": {
   "cogs": 358416.0,
   "current_assets": 66015010.0,
   "current_liabilities": 19973015.0,
   "current_ratio": 330.52,
   "debt_ratio": 57.55,
   "eps": -0.2,
   "eps_ttm": -0.26,
   "eps_yoy": 0.0,
   "equity": 47467659.0,
   "equity_parent": 47391330.0,
   "gross_margin": 44.89,
   "gross_profit": 291942.0,
   "net_income": -350146.0,
   "net_income_ttm": -471905.0,
   "net_income_yoy": -0.06,
   "net_margin": -53.84,
   "operating_expenses": 99583.0,
   "operating_income": 297121.0,
   "operating_income_yoy": 186.45,
   "operating_income_yoy_accel": 238.37,
   "operating_margin": 45.69,
   "pretax_income": -24005.0,
   "revenue": 650358.0,
   "revenue_ttm": 6999196.0,
   "revenue_yoy": 101.73,
   "revenue_yoy_accel": 143.08,
   "roa_q": -0.31,
   "roa_ttm": -0.42,
   "roe_q": -0.74,
   "roe_ttm": -0.99,
   "total_assets": 111812066.0,
   "total_liabilities": 64344407.0
  },
  "2023Q3": {
   "cogs": 1407151.0,
   "eps": 0.04,
   "eps_ttm": 0.02,
   "eps_yoy": 116.67,
   "gross_margin": 55.66,
   "gross_profit": 1766337.0,
   "net_income": 77085.0,
   "net_income_ttm": 27925.0,
   "net_income_yoy": 118.23,
   "net_margin": 2.43,
   "operating_expenses": 190196.0,
   "operating_income": 1576141.0,
   "operating_income_yoy": 663.67,
   "operating_income_yoy_accel": 477.22,
   "operating_margin": 49.67,
   "pretax_income": 1100306.0,
   "revenue": 3173488.0,
   "revenue_ttm": 9578696.0,
   "revenue_yoy": 434.27,
   "revenue_yoy_accel": 332.54
  },
  "2023Q4": {
   "cogs": 1729835.0,
   "eps": 0.26,
   "eps_ttm": 0.32,
   "eps_yoy": 750.0,
   "gross_margin": 59.68,
   "gross_profit": 2560839.0,
   "net_income": 461621.0,
   "net_income_ttm": 564999.0,
   "net_income_yoy": 711.8,
   "net_margin": 10.76,
   "operating_expenses": 103798.0,
   "operating_income": 2191536.0,
   "operating_income_yoy": 2986.54,
   "operating_income_yoy_accel": 2322.87,
   "operating_margin": 51.08,
   "pretax_income": 1781103.0,
   "revenue": 4290674.0,
   "revenue_ttm": 11732608.0,
   "revenue_yoy": 100.8,
   "revenue_yoy_accel": -333.47
  },
  "2024Q1": {
   "cogs": 1645057.0,
   "eps": 0.37,
   "eps_ttm": 0.47,
   "eps_yoy": 68.18,
   "gross_margin": 60.61,
   "gross_profit": 2531569.0,
   "net_income": 648639.0,
   "net_income_ttm": 837199.0,
   "net_income_yoy": 72.31,
   "net_margin": 15.53,
   "operating_expenses": 177516.0,
   "operating_income": 2354053.0,
   "operating_income_yoy": 39.81,
   "operating_income_yoy_accel": -2946.73,
   "operating_margin": 56.36,
   "pretax_income": 1983927.0,
   "revenue": 4176626.0,
   "revenue_ttm": 12291146.0,
   "revenue_yoy": 15.44,
   "revenue_yoy_accel": -85.36
  },
  "2024Q2": {
   "cogs": 510058.0,
   "eps": -0.25,
   "eps_ttm": 0.42,
   "eps_yoy": -25.0,
   "gross_margin": 32.99,
   "gross_profit": 251147.0,
   "net_income": -440761.0,
   "net_income_ttm": 746584.0,
   "net_income_yoy": -25.88,
   "net_margin": -57.9,
   "operating_expenses": 95077.0,
   "operating_income": -7060.0,
   "operating_income_yoy": -102.38,
   "operating_income_yoy_accel": -142.19,
   "operating_margin": -0.93,
   "pretax_income": -68794.0,
   "revenue": 761205.0,
   "revenue_ttm": 12401993.0,
   "revenue_yoy": 17.04,
   "revenue_yoy_accel": 1.6
  },
  "2024Q3": {
   "cogs": 1104485.0,
   "current_assets": 75272925.0,
   "current_liabilities": 22218814.0,
   "current_ratio": 338.78,
   "debt_ratio": 61.3,
   "eps": 0.03,
   "eps_ttm": 0.41,
   "eps_yoy": -25.0,
   "equity": 52118618.0,
   "equity_parent": 51156765.0,
   "gross_margin": 59.05,
   "gross_profit": 1592784.0,
   "net_income": 57029.0,
   "net_income_ttm": 726528.0,
   "net_income_yoy": -26.02,
   "net_margin": 2.11,
   "operating_expenses": 175382.0,
   "operating_income": 1417402.0,
   "operating_income_yoy": -10.07,
   "operating_income_yoy_accel": 92.31,
   "operating_margin": 52.55,
   "pretax_income": 915661.0,
   "revenue": 2697269.0,
   "revenue_ttm": 11925774.0,
   "revenue_yoy": -15.01,
   "revenue_yoy_accel": -32.05,
   "roa_q": 0.04,
   "roa_ttm": 0.54,
   "roe_q": 0.11,
   "roe_ttm": 1.39,
   "total_assets": 134665038.0,
   "total_liabilities": 82546420.0
  },
  "2024Q4": {
   "cogs": 288101.0,
   "current_assets": 72072844.0,
   "current_liabilities": 23409775.0,
   "current_ratio": 307.87,
   "debt_ratio": 60.15,
   "eps": 0.29,
   "eps_ttm": 0.44,
   "eps_yoy": 11.54,
   "equity": 51802566.0,
   "equity_parent": 50659634.0,
   "gross_margin": 68.97,
   "gross_profit": 640460.0,
   "net_income": 686867.0,
   "net_income_ttm": 951774.0,
   "net_income_yoy": 48.79,
   "net_margin": 73.97,
   "operating_expenses": 62364.0,
   "operating_income": -188562.0,
   "operating_income_yoy": -108.6,
   "operating_income_yoy_accel": -98.53,
   "operating_margin": -20.31,
   "pretax_income": 701684.0,
   "revenue": 928561.0,
   "revenue_ttm": 8563661.0,
   "revenue_yoy": -78.36,
   "revenue_yoy_accel": -63.35,
   "roa_q": 0.53,
   "roa_ttm": 0.73,
   "roe_q": 1.33,
   "roe_ttm": 1.84,
   "total_assets": 129993212.0,
   "total_liabilities": 78190646.0
  },
  "2025Q1": {
   "cogs": 393270.0,
   "current_assets": 72975725.0,
   "current_liabilities": 42072490.0,
   "current_ratio": 173.45,
   "debt_ratio": 60.28,
   "eps": -0.15,
   "eps_ttm": -0.08,
   "eps_yoy": -140.54,
   "equity": 52346065.0,
   "equity_parent": 51424544.0,
   "gross_margin": 51.76,
   "gross_profit": 422035.0,
   "net_income": -478442.0,
   "net_income_ttm": -175307.0,
   "net_income_yoy": -173.76,
   "net_margin": -58.68,
   "operating_expenses": 168959.0,
   "operating_income": 253076.0,
   "operating_income_yoy": -89.25,
   "operating_income_yoy_accel": 19.35,
   "operating_margin": 31.04,
   "pretax_income": -399060.0,
   "revenue": 815305.0,
   "revenue_ttm": 5202340.0,
   "revenue_yoy": -80.48,
   "revenue_yoy_accel": -2.12,
   "roa_q": -0.36,
   "roa_ttm": -0.13,
   "roe_q": -0.91,
   "roe_ttm": -0.33,
   "total_assets": 131790871.0,
   "total_liabilities": 79444806.0
  },
  "2025Q2": {
   "cogs": 556473.0,
   "current_assets": 64321624.0,
   "current_liabilities": 38218734.0,
   "current_ratio": 168.3,
   "debt_ratio": 60.46,
   "eps": -0.44,
   "eps_ttm": -0.27,
   "eps_yoy": -76.0,
   "equity": 46360493.0,
   "equity_parent": 45288641.0,
   "gross_margin": 27.26,
   "gross_profit": 208534.0,
   "net_income": -616771.0,
   "net_income_ttm": -351317.0,
   "net_income_yoy": -39.93,
   "net_margin": -80.62,
   "operating_expenses": 86647.0,
   "operating_income": -958503.0,
   "operating_income_yoy": -13476.53,
   "operating_income_yoy_accel": -13387.28,
   "operating_margin": -125.29,
   "pretax_income": -1008368.0,
   "revenue": 765007.0,
   "revenue_ttm": 5206142.0,
   "revenue_yoy": 0.5,
   "revenue_yoy_accel": 80.98,
   "roa_q": -0.53,
   "roa_ttm": -0.3,
   "roe_q": -1.33,
   "roe_ttm": -0.76,
   "total_assets": 117255469.0,
   "total_liabilities": 70894976.0
  },
  "2025Q3": {
   "cogs": 456671.0,
   "current_assets": 64300022.0,
   "current_liabilities": 35208299.0,
   "current_ratio": 182.63,
   "debt_ratio": 58.25,
   "eps": 0.14,
   "eps_ttm": -0.16,
   "eps_yoy": 366.67,
   "equity": 49730786.0,
   "equity_parent": 47506713.0,
   "gross_margin": 46.98,
   "gross_profit": 404690.0,
   "net_income": 448148.0,
   "net_income_ttm": 39802.0,
   "net_income_yoy": 685.82,
   "net_margin": 52.03,
   "operating_expenses": 113263.0,
   "operating_income": 277012.0,
   "operating_income_yoy": -80.46,
   "operating_income_yoy_accel": 13396.07,
   "operating_margin": 32.16,
   "pretax_income": 641818.0,
   "revenue": 861361.0,
   "revenue_ttm": 3370234.0,
   "revenue_yoy": -68.07,
   "revenue_yoy_accel": -68.57,
   "roa_q": 0.38,
   "roa_ttm": 0.03,
   "roe_q": 0.9,
   "roe_ttm": 0.08,
   "total_assets": 119120799.0,
   "total_liabilities": 69390013.0
  },
  "2025Q4": {
   "cogs": 1481280.0,
   "current_assets": 44513221.0,
   "current_liabilities": 16588209.0,
   "current_ratio": 268.34,
   "debt_ratio": 60.3,
   "eps": -3.17,
   "eps_ttm": -3.62,
   "eps_yoy": -1193.1,
   "equity": 46631518.0,
   "equity_parent": 44254697.0,
   "gross_margin": 55.83,
   "gross_profit": 1872378.0,
   "net_income": -5375027.0,
   "net_income_ttm": -6022092.0,
   "net_income_yoy": -882.54,
   "net_margin": -160.27,
   "operating_expenses": 170173.0,
   "operating_income": -5157777.0,
   "operating_income_yoy": -2635.32,
   "operating_income_yoy_accel": -2554.86,
   "operating_margin": -153.8,
   "pretax_income": -5225643.0,
   "revenue": 3353658.0,
   "revenue_ttm": 5795331.0,
   "revenue_yoy": 261.17,
   "revenue_yoy_accel": 329.24,
   "roa_q": -4.58,
   "roa_ttm": -5.13,
   "roe_q": -11.53,
   "roe_ttm": -12.91,
   "total_assets": 117466150.0,
   "total_liabilities": 70834632.0
  },
  "2026Q1": {
   "cogs": 844790.0,
   "current_assets": 43331856.0,
   "current_liabilities": 14759908.0,
   "current_ratio": 293.58,
   "debt_ratio": 59.07,
   "eps": 0.02,
   "eps_ttm": -3.45,
   "eps_yoy": 113.33,
   "equity": 48213990.0,
   "equity_parent": 45834714.0,
   "gross_margin": 59.16,
   "gross_profit": 1223647.0,
   "net_income": 29078.0,
   "net_income_ttm": -5514572.0,
   "net_income_yoy": 106.08,
   "net_margin": 1.41,
   "operating_expenses": 129929.0,
   "operating_income": 1093718.0,
   "operating_income_yoy": 332.17,
   "operating_income_yoy_accel": 2967.49,
   "operating_margin": 52.88,
   "pretax_income": 507741.0,
   "revenue": 2068437.0,
   "revenue_ttm": 7048463.0,
   "revenue_yoy": 153.7,
   "revenue_yoy_accel": -107.47,
   "roa_q": 0.02,
   "roa_ttm": -4.68,
   "roe_q": 0.06,
   "roe_ttm": -11.44,
   "total_assets": 117789596.0,
   "total_liabilities": 69575606.0
  }
 },
 "sector": "營建",
 "sector_parent": "傳產"
}