{
 "code": "3529",
 "industry": "半導體業",
 "monthly": {
  "2014-12": {
   "revenue": 17177.0
  },
  "2015-01": {
   "mom": 966.93,
   "revenue": 183266.0
  },
  "2015-02": {
   "mom": -73.91,
   "revenue": 47809.0
  },
  "2015-03": {
   "mom": -42.42,
   "revenue": 27527.0
  },
  "2015-04": {
   "mom": 527.65,
   "revenue": 172773.0
  },
  "2015-05": {
   "mom": -76.29,
   "revenue": 40969.0
  },
  "2015-06": {
   "mom": 62.52,
   "revenue": 66583.0
  },
  "2015-07": {
   "mom": 190.33,
   "revenue": 193311.0
  },
  "2015-08": {
   "mom": -76.62,
   "revenue": 45204.0
  },
  "2015-09": {
   "mom": -70.58,
   "revenue": 13300.0
  },
  "2015-10": {
   "mom": 1594.29,
   "revenue": 225341.0
  },
  "2015-11": {
   "mom": -77.81,
   "revenue": 49992.0
  },
  "2015-12": {
   "mom": -48.9,
   "revenue": 25545.0,
   "yoy": 48.72
  },
  "2016-01": {
   "mom": 798.39,
   "revenue": 229494.0,
   "yoy": 25.22
  },
  "2016-02": {
   "mom": -80.51,
   "revenue": 44718.0,
   "yoy": -6.47
  },
  "2016-03": {
   "mom": 2.05,
   "revenue": 45634.0,
   "yoy": 65.78
  },
  "2016-04": {
   "mom": 342.35,
   "revenue": 201860.0,
   "yoy": 16.84
  },
  "2016-05": {
   "mom": -72.14,
   "revenue": 56240.0,
   "yoy": 37.27
  },
  "2016-06": {
   "mom": -61.03,
   "revenue": 21919.0,
   "yoy": -67.08
  },
  "2016-07": {
   "mom": 907.61,
   "revenue": 220858.0,
   "yoy": 14.25
  },
  "2016-08": {
   "mom": -70.76,
   "revenue": 64583.0,
   "yoy": 42.87
  },
  "2016-09": {
   "mom": -62.95,
   "revenue": 23926.0,
   "yoy": 79.89
  },
  "2016-10": {
   "mom": 788.79,
   "revenue": 212651.0,
   "yoy": -5.63
  },
  "2016-11": {
   "mom": -69.22,
   "revenue": 65444.0,
   "yoy": 30.91
  },
  "2016-12": {
   "mom": -57.01,
   "revenue": 28132.0,
   "yoy": 10.13
  },
  "2017-01": {
   "mom": 756.14,
   "revenue": 240849.0,
   "yoy": 4.95
  },
  "2017-02": {
   "mom": -70.84,
   "revenue": 70240.0,
   "yoy": 57.07
  },
  "2017-03": {
   "mom": -62.76,
   "revenue": 26160.0,
   "yoy": -42.67
  },
  "2017-04": {
   "mom": 641.42,
   "revenue": 193955.0,
   "yoy": -3.92
  },
  "2017-05": {
   "mom": -63.78,
   "revenue": 70244.0,
   "yoy": 24.9
  },
  "2017-06": {
   "mom": -3.16,
   "revenue": 68021.0,
   "yoy": 210.33
  },
  "2017-07": {
   "mom": 328.52,
   "revenue": 291486.0,
   "yoy": 31.98
  },
  "2017-08": {
   "mom": -76.59,
   "revenue": 68232.0,
   "yoy": 5.65
  },
  "2017-09": {
   "mom": -63.79,
   "revenue": 24705.0,
   "yoy": 3.26
  },
  "2017-10": {
   "mom": 830.44,
   "revenue": 229864.0,
   "yoy": 8.09
  },
  "2017-11": {
   "mom": -70.68,
   "revenue": 67387.0,
   "yoy": 2.97
  },
  "2017-12": {
   "mom": -63.47,
   "revenue": 24615.0,
   "yoy": -12.5
  },
  "2018-01": {
   "mom": 969.1,
   "revenue": 263159.0,
   "yoy": 9.26
  },
  "2018-02": {
   "mom": -74.69,
   "revenue": 66604.0,
   "yoy": -5.18
  },
  "2018-03": {
   "mom": -32.88,
   "revenue": 44703.0,
   "yoy": 70.88
  },
  "2018-04": {
   "mom": 312.44,
   "revenue": 184375.0,
   "yoy": -4.94
  },
  "2018-05": {
   "mom": -57.35,
   "revenue": 78631.0,
   "yoy": 11.94
  },
  "2018-06": {
   "mom": -50.32,
   "revenue": 39067.0,
   "yoy": -42.57
  },
  "2018-07": {
   "mom": 633.69,
   "revenue": 286629.0,
   "yoy": -1.67
  },
  "2018-08": {
   "mom": -73.84,
   "revenue": 74979.0,
   "yoy": 9.89
  },
  "2018-09": {
   "mom": -57.83,
   "revenue": 31617.0,
   "yoy": 27.98
  },
  "2018-10": {
   "mom": 801.22,
   "revenue": 284940.0,
   "yoy": 23.96
  },
  "2018-11": {
   "mom": -69.78,
   "revenue": 86118.0,
   "yoy": 27.8
  },
  "2018-12": {
   "mom": -58.55,
   "revenue": 35694.0,
   "yoy": 45.01
  },
  "2019-01": {
   "mom": 701.82,
   "revenue": 286201.0,
   "yoy": 8.76
  },
  "2019-02": {
   "mom": -79.42,
   "revenue": 58900.0,
   "yoy": -11.57
  },
  "2019-03": {
   "mom": -15.18,
   "revenue": 49960.0,
   "yoy": 11.76
  },
  "2019-04": {
   "mom": 294.96,
   "revenue": 197324.0,
   "yoy": 7.02
  },
  "2019-05": {
   "mom": -58.38,
   "revenue": 82136.0,
   "yoy": 4.46
  },
  "2019-06": {
   "mom": -54.85,
   "revenue": 37081.0,
   "yoy": -5.08
  },
  "2019-07": {
   "mom": 509.46,
   "revenue": 225993.0,
   "yoy": -21.15
  },
  "2019-08": {
   "mom": -63.64,
   "revenue": 82180.0,
   "yoy": 9.6
  },
  "2019-09": {
   "mom": -65.42,
   "revenue": 28414.0,
   "yoy": -10.13
  },
  "2019-10": {
   "mom": 728.54,
   "revenue": 235420.0,
   "yoy": -17.38
  },
  "2019-11": {
   "mom": -59.7,
   "revenue": 94884.0,
   "yoy": 10.18
  },
  "2019-12": {
   "mom": -66.7,
   "revenue": 31592.0,
   "yoy": -11.49
  },
  "2020-01": {
   "mom": 818.14,
   "revenue": 290059.0,
   "yoy": 1.35
  },
  "2020-02": {
   "mom": -71.07,
   "revenue": 83900.0,
   "yoy": 42.44
  },
  "2020-03": {
   "mom": -50.56,
   "revenue": 41477.0,
   "yoy": -16.98
  },
  "2020-04": {
   "mom": 483.28,
   "revenue": 241928.0,
   "yoy": 22.6
  },
  "2020-05": {
   "mom": -44.97,
   "revenue": 133136.0,
   "yoy": 62.09
  },
  "2020-06": {
   "mom": -63.79,
   "revenue": 48212.0,
   "yoy": 30.02
  },
  "2020-07": {
   "mom": 538.95,
   "revenue": 308050.0,
   "yoy": 36.31
  },
  "2020-08": {
   "mom": -71.44,
   "revenue": 87974.0,
   "yoy": 7.05
  },
  "2020-09": {
   "mom": -48.58,
   "revenue": 45235.0,
   "yoy": 59.2
  },
  "2020-10": {
   "mom": 584.14,
   "revenue": 309469.0,
   "yoy": 31.45
  },
  "2020-11": {
   "mom": -56.56,
   "revenue": 134443.0,
   "yoy": 41.69
  },
  "2020-12": {
   "mom": -60.75,
   "revenue": 52770.0,
   "yoy": 67.04
  },
  "2021-01": {
   "mom": 695.11,
   "revenue": 419581.0,
   "yoy": 44.65
  },
  "2021-02": {
   "mom": -70.27,
   "revenue": 124733.0,
   "yoy": 48.67
  },
  "2021-03": {
   "mom": -57.97,
   "revenue": 52420.0,
   "yoy": 26.38
  },
  "2021-04": {
   "mom": 519.98,
   "revenue": 324995.0,
   "yoy": 34.34
  },
  "2021-05": {
   "mom": -51.0,
   "revenue": 159243.0,
   "yoy": 19.61
  },
  "2021-06": {
   "mom": -64.09,
   "revenue": 57177.0,
   "yoy": 18.59
  },
  "2021-07": {
   "mom": 551.48,
   "revenue": 372498.0,
   "yoy": 20.92
  },
  "2021-08": {
   "mom": -55.8,
   "revenue": 164633.0,
   "yoy": 87.14
  },
  "2021-09": {
   "mom": -65.29,
   "revenue": 57146.0,
   "yoy": 26.33
  },
  "2021-10": {
   "mom": 561.79,
   "revenue": 378185.0,
   "yoy": 22.2
  },
  "2021-11": {
   "mom": -51.29,
   "revenue": 184210.0,
   "yoy": 37.02
  },
  "2021-12": {
   "mom": -62.54,
   "revenue": 69003.0,
   "yoy": 30.76
  },
  "2022-01": {
   "mom": 528.27,
   "revenue": 433528.0,
   "yoy": 3.32
  },
  "2022-02": {
   "mom": -45.46,
   "revenue": 236425.0,
   "yoy": 89.54
  },
  "2022-03": {
   "mom": -75.83,
   "revenue": 57154.0,
   "yoy": 9.03
  },
  "2022-04": {
   "mom": 729.65,
   "revenue": 474179.0,
   "yoy": 45.9
  },
  "2022-05": {
   "mom": -50.8,
   "revenue": 233284.0,
   "yoy": 46.5
  },
  "2022-06": {
   "mom": -61.92,
   "revenue": 88829.0,
   "yoy": 55.36
  },
  "2022-07": {
   "mom": 454.37,
   "revenue": 492441.0,
   "yoy": 32.2
  },
  "2022-08": {
   "mom": -51.29,
   "revenue": 239863.0,
   "yoy": 45.7
  },
  "2022-09": {
   "mom": -75.69,
   "revenue": 58304.0,
   "yoy": 2.03
  },
  "2022-10": {
   "mom": 791.48,
   "revenue": 519769.0,
   "yoy": 37.44
  },
  "2022-11": {
   "mom": -48.12,
   "revenue": 269670.0,
   "yoy": 46.39
  },
  "2022-12": {
   "mom": -58.0,
   "revenue": 113265.0,
   "yoy": 64.15
  },
  "2023-01": {
   "mom": 248.1,
   "revenue": 394270.0,
   "yoy": -9.06
  },
  "2023-02": {
   "mom": -45.87,
   "revenue": 213435.0,
   "yoy": -9.72
  },
  "2023-03": {
   "mom": -71.87,
   "revenue": 60046.0,
   "yoy": 5.06
  },
  "2023-04": {
   "mom": 493.05,
   "revenue": 356102.0,
   "yoy": -24.9
  },
  "2023-05": {
   "mom": -28.4,
   "revenue": 254958.0,
   "yoy": 9.29
  },
  "2023-06": {
   "mom": -66.44,
   "revenue": 85565.0,
   "yoy": -3.67
  },
  "2023-07": {
   "mom": 400.99,
   "revenue": 428676.0,
   "yoy": -12.95
  },
  "2023-08": {
   "mom": -38.67,
   "revenue": 262919.0,
   "yoy": 9.61
  },
  "2023-09": {
   "mom": -63.68,
   "revenue": 95496.0,
   "yoy": 63.79
  },
  "2023-10": {
   "mom": 418.7,
   "revenue": 495333.0,
   "yoy": -4.7
  },
  "2023-11": {
   "mom": -42.9,
   "revenue": 282825.0,
   "yoy": 4.88
  },
  "2023-12": {
   "mom": -57.32,
   "revenue": 120700.0,
   "yoy": 6.56
  },
  "2024-01": {
   "mom": 275.61,
   "revenue": 453365.0,
   "yoy": 14.99
  },
  "2024-02": {
   "mom": -42.16,
   "revenue": 262246.0,
   "yoy": 22.87
  },
  "2024-03": {
   "mom": -66.77,
   "revenue": 87153.0,
   "yoy": 45.14
  },
  "2024-04": {
   "mom": 459.54,
   "revenue": 487655.0,
   "yoy": 36.94
  },
  "2024-05": {
   "mom": -41.87,
   "revenue": 283455.0,
   "yoy": 11.18
  },
  "2024-06": {
   "mom": -56.99,
   "revenue": 121900.0,
   "yoy": 42.46
  },
  "2024-07": {
   "mom": 317.84,
   "revenue": 509347.0,
   "yoy": 18.82
  },
  "2024-08": {
   "mom": -43.51,
   "revenue": 287741.0,
   "yoy": 9.44
  },
  "2024-09": {
   "mom": -64.42,
   "revenue": 102389.0,
   "yoy": 7.22
  },
  "2024-10": {
   "mom": 448.42,
   "revenue": 561522.0,
   "yoy": 13.36
  },
  "2024-11": {
   "mom": -42.6,
   "revenue": 322319.0,
   "yoy": 13.96
  },
  "2024-12": {
   "mom": -60.64,
   "revenue": 126876.0,
   "yoy": 5.12
  },
  "2025-01": {
   "mom": 329.56,
   "revenue": 545007.0,
   "yoy": 20.21
  },
  "2025-02": {
   "mom": -49.77,
   "revenue": 273771.0,
   "yoy": 4.39
  },
  "2025-03": {
   "mom": -66.05,
   "revenue": 92956.0,
   "yoy": 6.66
  },
  "2025-04": {
   "mom": 484.04,
   "revenue": 542896.0,
   "yoy": 11.33
  },
  "2025-05": {
   "mom": -49.85,
   "revenue": 272282.0,
   "yoy": -3.94
  },
  "2025-06": {
   "mom": -55.43,
   "revenue": 121357.0,
   "yoy": -0.45
  },
  "2025-07": {
   "mom": 349.98,
   "revenue": 546080.0,
   "yoy": 7.21
  },
  "2025-08": {
   "mom": -54.22,
   "revenue": 249996.0,
   "yoy": -13.12
  },
  "2025-09": {
   "mom": -37.46,
   "revenue": 156346.0,
   "yoy": 52.7
  },
  "2025-10": {
   "mom": 298.26,
   "revenue": 622668.0,
   "yoy": 10.89
  },
  "2025-11": {
   "mom": -44.48,
   "revenue": 345683.0,
   "yoy": 7.25
  },
  "2025-12": {
   "mom": -76.85,
   "revenue": 80011.0,
   "yoy": -36.94
  },
  "2026-01": {
   "mom": 733.65,
   "revenue": 667012.0,
   "yoy": 22.39
  },
  "2026-02": {
   "mom": -54.15,
   "revenue": 305812.0,
   "yoy": 11.7
  },
  "2026-03": {
   "mom": -60.38,
   "revenue": 121169.0,
   "yoy": 30.35
  },
  "2026-04": {
   "mom": 406.0,
   "revenue": 613115.0,
   "yoy": 12.93
  },
  "2026-05": {
   "mom": -50.24,
   "revenue": 305058,
   "yoy": 12.04
  }
 },
 "name": "力旺",
 "quarterly": {
  "2015Q1": {
   "cogs": 0.0,
   "current_assets": 1513466.0,
   "current_liabilities": 194707.0,
   "current_ratio": 777.3,
   "debt_ratio": 9.9,
   "eps": 1.51,
   "equity": 1909669.0,
   "equity_parent": 1909669.0,
   "gross_margin": 100.0,
   "gross_profit": 258602.0,
   "net_income": 114423.0,
   "net_margin": 44.25,
   "operating_expenses": 128976.0,
   "operating_income": 129626.0,
   "operating_margin": 50.13,
   "pretax_income": 129676.0,
   "revenue": 258602.0,
   "roa_q": 5.4,
   "roe_q": 5.99,
   "total_assets": 2119460.0,
   "total_liabilities": 209791.0
  },
  "2015Q2": {
   "cogs": 0.0,
   "current_assets": 1676770.0,
   "current_liabilities": 674357.0,
   "current_ratio": 248.65,
   "debt_ratio": 30.32,
   "eps": 1.72,
   "equity": 1585274.0,
   "equity_parent": 1585274.0,
   "gross_margin": 100.0,
   "gross_profit": 280325.0,
   "net_income": 130297.0,
   "net_margin": 46.48,
   "operating_expenses": 141435.0,
   "operating_income": 138890.0,
   "operating_margin": 49.55,
   "pretax_income": 147199.0,
   "revenue": 280325.0,
   "roa_q": 5.73,
   "roe_q": 8.22,
   "total_assets": 2275140.0,
   "total_liabilities": 689866.0
  },
  "2015Q3": {
   "cogs": 0.0,
   "current_assets": 1298260.0,
   "current_liabilities": 183258.0,
   "current_ratio": 708.43,
   "debt_ratio": 10.51,
   "eps": 1.4,
   "equity": 1691575.0,
   "equity_parent": 1691575.0,
   "gross_margin": 100.0,
   "gross_profit": 251815.0,
   "net_income": 106301.0,
   "net_margin": 42.21,
   "operating_expenses": 143776.0,
   "operating_income": 108039.0,
   "operating_margin": 42.9,
   "pretax_income": 121376.0,
   "revenue": 251815.0,
   "roa_q": 5.62,
   "roe_q": 6.28,
   "total_assets": 1890342.0,
   "total_liabilities": 198767.0
  },
  "2015Q4": {
   "cogs": 0.0,
   "current_assets": 1439253.0,
   "current_liabilities": 200260.0,
   "current_ratio": 718.69,
   "debt_ratio": 10.74,
   "eps": 1.69,
   "eps_ttm": 6.32,
   "equity": 1816782.0,
   "equity_parent": 1816782.0,
   "gross_margin": 100.0,
   "gross_profit": 300878.0,
   "net_income": 128090.0,
   "net_income_ttm": 479111.0,
   "net_margin": 42.57,
   "operating_expenses": 156216.0,
   "operating_income": 144662.0,
   "operating_margin": 48.08,
   "pretax_income": 145036.0,
   "revenue": 300878.0,
   "revenue_ttm": 1091620.0,
   "roa_q": 6.29,
   "roa_ttm": 23.54,
   "roe_q": 7.05,
   "roe_ttm": 26.37,
   "total_assets": 2035473.0,
   "total_liabilities": 218691.0
  },
  "2016Q1": {
   "cogs": 0.0,
   "current_assets": 1660530.0,
   "current_liabilities": 248653.0,
   "current_ratio": 667.81,
   "debt_ratio": 11.82,
   "eps": 2.19,
   "eps_ttm": 7.0,
   "eps_yoy": 45.03,
   "equity": 1992451.0,
   "equity_parent": 1992451.0,
   "gross_margin": 100.0,
   "gross_profit": 319846.0,
   "net_income": 166012.0,
   "net_income_ttm": 530700.0,
   "net_income_yoy": 45.09,
   "net_margin": 51.9,
   "operating_expenses": 177088.0,
   "operating_income": 142758.0,
   "operating_income_yoy": 10.13,
   "operating_margin": 44.63,
   "pretax_income": 185595.0,
   "revenue": 319846.0,
   "revenue_ttm": 1152864.0,
   "revenue_yoy": 23.68,
   "roa_q": 7.35,
   "roa_ttm": 23.49,
   "roe_q": 8.33,
   "roe_ttm": 26.64,
   "total_assets": 2259459.0,
   "total_liabilities": 267008.0
  },
  "2016Q2": {
   "cogs": 0.0,
   "current_assets": 1799614.0,
   "current_liabilities": 732294.0,
   "current_ratio": 245.75,
   "debt_ratio": 31.26,
   "eps": 1.4,
   "eps_ttm": 6.68,
   "eps_yoy": -18.6,
   "equity": 1650605.0,
   "equity_parent": 1650605.0,
   "gross_margin": 100.0,
   "gross_profit": 280019.0,
   "net_income": 106245.0,
   "net_income_ttm": 506648.0,
   "net_income_yoy": -18.46,
   "net_margin": 37.94,
   "operating_expenses": 163276.0,
   "operating_income": 116743.0,
   "operating_income_yoy": -15.95,
   "operating_income_yoy_accel": -26.08,
   "operating_margin": 41.69,
   "pretax_income": 121479.0,
   "revenue": 280019.0,
   "revenue_ttm": 1152558.0,
   "revenue_yoy": -0.11,
   "revenue_yoy_accel": -23.79,
   "roa_q": 4.42,
   "roa_ttm": 21.1,
   "roe_q": 6.44,
   "roe_ttm": 30.69,
   "total_assets": 2401128.0,
   "total_liabilities": 750523.0
  },
  "2016Q3": {
   "cogs": 0.0,
   "current_assets": 1446909.0,
   "current_liabilities": 241672.0,
   "current_ratio": 598.71,
   "debt_ratio": 12.67,
   "eps": 1.72,
   "eps_ttm": 7.0,
   "eps_yoy": 22.86,
   "equity": 1787506.0,
   "equity_parent": 1787506.0,
   "gross_margin": 100.0,
   "gross_profit": 309367.0,
   "net_income": 130299.0,
   "net_income_ttm": 530646.0,
   "net_income_yoy": 22.58,
   "net_margin": 42.12,
   "operating_expenses": 173605.0,
   "operating_income": 135762.0,
   "operating_income_yoy": 25.66,
   "operating_income_yoy_accel": 41.61,
   "operating_margin": 43.88,
   "pretax_income": 147276.0,
   "revenue": 309367.0,
   "revenue_ttm": 1210110.0,
   "revenue_yoy": 22.85,
   "revenue_yoy_accel": 22.96,
   "roa_q": 6.37,
   "roa_ttm": 25.92,
   "roe_q": 7.29,
   "roe_ttm": 29.69,
   "total_assets": 2046853.0,
   "total_liabilities": 259347.0
  },
  "2016Q4": {
   "cogs": 0.0,
   "eps": 1.75,
   "eps_ttm": 7.06,
   "eps_yoy": 3.55,
   "gross_margin": 100.0,
   "gross_profit": 306227.0,
   "net_income": 132361.0,
   "net_income_ttm": 534917.0,
   "net_income_yoy": 3.33,
   "net_margin": 43.22,
   "operating_expenses": 171681.0,
   "operating_income": 134546.0,
   "operating_income_yoy": -6.99,
   "operating_income_yoy_accel": -32.65,
   "operating_margin": 43.94,
   "pretax_income": 153892.0,
   "revenue": 306227.0,
   "revenue_ttm": 1215459.0,
   "revenue_yoy": 1.78,
   "revenue_yoy_accel": -21.07
  },
  "2017Q1": {
   "cogs": 0.0,
   "current_assets": 1742684.0,
   "current_liabilities": 253130.0,
   "current_ratio": 688.45,
   "debt_ratio": 11.59,
   "eps": 2.0,
   "eps_ttm": 6.87,
   "eps_yoy": -8.68,
   "equity": 2081628.0,
   "equity_parent": 2081628.0,
   "gross_margin": 100.0,
   "gross_profit": 337249.0,
   "net_income": 151378.0,
   "net_income_ttm": 520283.0,
   "net_income_yoy": -8.82,
   "net_margin": 44.89,
   "operating_expenses": 193603.0,
   "operating_income": 143646.0,
   "operating_income_yoy": 0.62,
   "operating_income_yoy_accel": 7.61,
   "operating_margin": 42.59,
   "pretax_income": 170793.0,
   "revenue": 337249.0,
   "revenue_ttm": 1232862.0,
   "revenue_yoy": 5.44,
   "revenue_yoy_accel": 3.66,
   "roa_q": 6.43,
   "roa_ttm": 22.1,
   "roe_q": 7.27,
   "roe_ttm": 24.99,
   "total_assets": 2354552.0,
   "total_liabilities": 272924.0
  },
  "2017Q2": {
   "cogs": 0.0,
   "current_assets": 1932143.0,
   "current_liabilities": 785846.0,
   "current_ratio": 245.87,
   "debt_ratio": 31.62,
   "eps": 1.79,
   "eps_ttm": 7.26,
   "eps_yoy": 27.86,
   "equity": 1741071.0,
   "equity_parent": 1741071.0,
   "gross_margin": 100.0,
   "gross_profit": 332220.0,
   "net_income": 135610.0,
   "net_income_ttm": 549648.0,
   "net_income_yoy": 27.64,
   "net_margin": 40.82,
   "operating_expenses": 188562.0,
   "operating_income": 143658.0,
   "operating_income_yoy": 23.05,
   "operating_income_yoy_accel": 22.43,
   "operating_margin": 43.24,
   "pretax_income": 155679.0,
   "revenue": 332220.0,
   "revenue_ttm": 1285063.0,
   "revenue_yoy": 18.64,
   "revenue_yoy_accel": 13.2,
   "roa_q": 5.33,
   "roa_ttm": 21.59,
   "roe_q": 7.79,
   "roe_ttm": 31.57,
   "total_assets": 2546169.0,
   "total_liabilities": 805098.0
  },
  "2017Q3": {
   "cogs": 0.0,
   "eps": 2.56,
   "eps_ttm": 8.1,
   "eps_yoy": 48.84,
   "gross_margin": 100.0,
   "gross_profit": 384423.0,
   "net_income": 194062.0,
   "net_income_ttm": 613411.0,
   "net_income_yoy": 48.94,
   "net_margin": 50.48,
   "operating_expenses": 205291.0,
   "operating_income": 179132.0,
   "operating_income_yoy": 31.95,
   "operating_income_yoy_accel": 8.9,
   "operating_margin": 46.6,
   "pretax_income": 216769.0,
   "revenue": 384423.0,
   "revenue_ttm": 1360119.0,
   "revenue_yoy": 24.26,
   "revenue_yoy_accel": 5.62
  },
  "2017Q4": {
   "cogs": 0.0,
   "eps": 1.55,
   "eps_ttm": 7.9,
   "eps_yoy": -11.43,
   "gross_margin": 100.0,
   "gross_profit": 321866.0,
   "net_income": 117659.0,
   "net_income_ttm": 598709.0,
   "net_income_yoy": -11.11,
   "net_margin": 36.56,
   "operating_expenses": 185484.0,
   "operating_income": 136382.0,
   "operating_income_yoy": 1.36,
   "operating_income_yoy_accel": -30.59,
   "operating_margin": 42.37,
   "pretax_income": 136559.0,
   "revenue": 321866.0,
   "revenue_ttm": 1375758.0,
   "revenue_yoy": 5.11,
   "revenue_yoy_accel": -19.15
  },
  "2018Q1": {
   "cogs": 0.0,
   "eps": 2.23,
   "eps_ttm": 8.13,
   "eps_yoy": 11.5,
   "gross_margin": 100.0,
   "gross_profit": 374466.0,
   "net_income": 168730.0,
   "net_income_ttm": 616061.0,
   "net_income_yoy": 11.46,
   "net_margin": 45.06,
   "operating_expenses": 193201.0,
   "operating_income": 181265.0,
   "operating_income_yoy": 26.19,
   "operating_income_yoy_accel": 24.83,
   "operating_margin": 48.41,
   "pretax_income": 191102.0,
   "revenue": 374466.0,
   "revenue_ttm": 1412975.0,
   "revenue_yoy": 11.04,
   "revenue_yoy_accel": 5.93
  },
  "2018Q2": {
   "cogs": 0.0,
   "eps": 1.48,
   "eps_ttm": 7.82,
   "eps_yoy": -17.32,
   "gross_margin": 100.0,
   "gross_profit": 302073.0,
   "net_income": 112193.0,
   "net_income_ttm": 592644.0,
   "net_income_yoy": -17.27,
   "net_margin": 37.14,
   "operating_expenses": 183706.0,
   "operating_income": 118367.0,
   "operating_income_yoy": -17.61,
   "operating_income_yoy_accel": -43.8,
   "operating_margin": 39.18,
   "pretax_income": 128154.0,
   "revenue": 302073.0,
   "revenue_ttm": 1382828.0,
   "revenue_yoy": -9.07,
   "revenue_yoy_accel": -20.11
  },
  "2018Q3": {
   "cogs": 0.0,
   "eps": 2.23,
   "eps_ttm": 7.49,
   "eps_yoy": -12.89,
   "gross_margin": 100.0,
   "gross_profit": 393225.0,
   "net_income": 168572.0,
   "net_income_ttm": 567154.0,
   "net_income_yoy": -13.13,
   "net_margin": 42.87,
   "operating_expenses": 204342.0,
   "operating_income": 188883.0,
   "operating_income_yoy": 5.44,
   "operating_income_yoy_accel": 23.05,
   "operating_margin": 48.03,
   "pretax_income": 192215.0,
   "revenue": 393225.0,
   "revenue_ttm": 1391630.0,
   "revenue_yoy": 2.29,
   "revenue_yoy_accel": 11.36
  },
  "2018Q4": {
   "cogs": 0.0,
   "current_assets": 1483605.0,
   "current_liabilities": 349772.0,
   "current_ratio": 424.16,
   "debt_ratio": 17.61,
   "eps": 2.2,
   "eps_ttm": 8.14,
   "eps_yoy": 41.94,
   "equity": 1733541.0,
   "equity_parent": 1733541.0,
   "gross_margin": 100.0,
   "gross_profit": 406752.0,
   "net_income": 163611.0,
   "net_income_ttm": 613106.0,
   "net_income_yoy": 39.06,
   "net_margin": 40.22,
   "operating_expenses": 222532.0,
   "operating_income": 184220.0,
   "operating_income_yoy": 35.08,
   "operating_income_yoy_accel": 29.64,
   "operating_margin": 45.29,
   "pretax_income": 187360.0,
   "revenue": 406752.0,
   "revenue_ttm": 1476516.0,
   "revenue_yoy": 26.37,
   "revenue_yoy_accel": 24.08,
   "roa_q": 7.78,
   "roa_ttm": 29.14,
   "roe_q": 9.44,
   "roe_ttm": 35.37,
   "total_assets": 2104177.0,
   "total_liabilities": 370636.0
  },
  "2019Q1": {
   "cogs": 0.0,
   "eps": 2.39,
   "eps_ttm": 8.3,
   "eps_yoy": 7.17,
   "gross_margin": 100.0,
   "gross_profit": 395061.0,
   "net_income": 177151.0,
   "net_income_ttm": 621527.0,
   "net_income_yoy": 4.99,
   "net_margin": 44.84,
   "operating_expenses": 201088.0,
   "operating_income": 193973.0,
   "operating_income_yoy": 7.01,
   "operating_income_yoy_accel": -28.07,
   "operating_margin": 49.1,
   "pretax_income": 203206.0,
   "revenue": 395061.0,
   "revenue_ttm": 1497111.0,
   "revenue_yoy": 5.5,
   "revenue_yoy_accel": -20.87
  },
  "2019Q2": {
   "cogs": 0.0,
   "eps": 1.55,
   "eps_ttm": 8.37,
   "eps_yoy": 4.73,
   "gross_margin": 100.0,
   "gross_profit": 316541.0,
   "net_income": 115098.0,
   "net_income_ttm": 624432.0,
   "net_income_yoy": 2.59,
   "net_margin": 36.36,
   "operating_expenses": 187889.0,
   "operating_income": 128652.0,
   "operating_income_yoy": 8.69,
   "operating_income_yoy_accel": 1.68,
   "operating_margin": 40.64,
   "pretax_income": 133252.0,
   "revenue": 316541.0,
   "revenue_ttm": 1511579.0,
   "revenue_yoy": 4.79,
   "revenue_yoy_accel": -0.71
  },
  "2019Q3": {
   "cogs": 0.0,
   "current_assets": 1294349.0,
   "current_liabilities": 312710.0,
   "current_ratio": 413.91,
   "debt_ratio": 17.71,
   "eps": 1.62,
   "eps_ttm": 7.76,
   "eps_yoy": -27.35,
   "equity": 1571877.0,
   "equity_parent": 1571877.0,
   "gross_margin": 100.0,
   "gross_profit": 336587.0,
   "net_income": 120170.0,
   "net_income_ttm": 576030.0,
   "net_income_yoy": -28.71,
   "net_margin": 35.7,
   "operating_expenses": 197399.0,
   "operating_income": 139188.0,
   "operating_income_yoy": -26.31,
   "operating_income_yoy_accel": -35.0,
   "operating_margin": 41.35,
   "pretax_income": 140573.0,
   "revenue": 336587.0,
   "revenue_ttm": 1454941.0,
   "revenue_yoy": -14.4,
   "revenue_yoy_accel": -19.19,
   "roa_q": 6.29,
   "roa_ttm": 30.16,
   "roe_q": 7.65,
   "roe_ttm": 36.65,
   "total_assets": 1910063.0,
   "total_liabilities": 338186.0
  },
  "2019Q4": {
   "cogs": 0.0,
   "current_assets": 1416756.0,
   "current_liabilities": 305153.0,
   "current_ratio": 464.28,
   "debt_ratio": 16.29,
   "eps": 1.74,
   "eps_ttm": 7.3,
   "eps_yoy": -20.91,
   "equity": 1702014.0,
   "equity_parent": 1702014.0,
   "gross_margin": 100.0,
   "gross_profit": 361896.0,
   "net_income": 129653.0,
   "net_income_ttm": 542072.0,
   "net_income_yoy": -20.76,
   "net_margin": 35.83,
   "operating_expenses": 202386.0,
   "operating_income": 159510.0,
   "operating_income_yoy": -13.41,
   "operating_income_yoy_accel": 12.9,
   "operating_margin": 44.08,
   "pretax_income": 156153.0,
   "revenue": 361896.0,
   "revenue_ttm": 1410085.0,
   "revenue_yoy": -11.03,
   "revenue_yoy_accel": 3.37,
   "roa_q": 6.38,
   "roa_ttm": 26.66,
   "roe_q": 7.62,
   "roe_ttm": 31.85,
   "total_assets": 2033327.0,
   "total_liabilities": 331313.0
  },
  "2020Q1": {
   "cogs": 0.0,
   "current_assets": 1694080.0,
   "current_liabilities": 364071.0,
   "current_ratio": 465.32,
   "debt_ratio": 17.16,
   "eps": 2.38,
   "eps_ttm": 7.29,
   "eps_yoy": -0.42,
   "equity": 1880312.0,
   "equity_parent": 1880290.0,
   "gross_margin": 100.0,
   "gross_profit": 415436.0,
   "net_income": 176758.0,
   "net_income_ttm": 541679.0,
   "net_income_yoy": -0.22,
   "net_margin": 42.55,
   "operating_expenses": 221463.0,
   "operating_income": 193973.0,
   "operating_income_yoy": 0.0,
   "operating_income_yoy_accel": 13.41,
   "operating_margin": 46.69,
   "pretax_income": 202356.0,
   "revenue": 415436.0,
   "revenue_ttm": 1430460.0,
   "revenue_yoy": 5.16,
   "revenue_yoy_accel": 16.19,
   "roa_q": 7.79,
   "roa_ttm": 23.86,
   "roe_q": 9.4,
   "roe_ttm": 28.81,
   "total_assets": 2269773.0,
   "total_liabilities": 389461.0
  },
  "2020Q2": {
   "cogs": 0.0,
   "current_assets": 1873936.0,
   "current_liabilities": 896232.0,
   "current_ratio": 209.09,
   "debt_ratio": 37.57,
   "eps": 2.28,
   "eps_ttm": 8.02,
   "eps_yoy": 47.1,
   "equity": 1530757.0,
   "equity_parent": 1530712.0,
   "gross_margin": 100.0,
   "gross_profit": 423276.0,
   "net_income": 169317.0,
   "net_income_ttm": 595898.0,
   "net_income_yoy": 47.11,
   "net_margin": 40.0,
   "operating_expenses": 227364.0,
   "operating_income": 195912.0,
   "operating_income_yoy": 52.28,
   "operating_income_yoy_accel": 52.28,
   "operating_margin": 46.28,
   "pretax_income": 198732.0,
   "revenue": 423276.0,
   "revenue_ttm": 1537195.0,
   "revenue_yoy": 33.72,
   "revenue_yoy_accel": 28.56,
   "roa_q": 6.91,
   "roa_ttm": 24.3,
   "roe_q": 11.06,
   "roe_ttm": 38.93,
   "total_assets": 2451898.0,
   "total_liabilities": 921141.0
  },
  "2020Q3": {
   "cogs": 0.0,
   "current_assets": 1637969.0,
   "current_liabilities": 404853.0,
   "current_ratio": 404.58,
   "debt_ratio": 19.36,
   "eps": 2.26,
   "eps_ttm": 8.66,
   "eps_yoy": 39.51,
   "equity": 1785457.0,
   "equity_parent": 1770388.0,
   "gross_margin": 100.0,
   "gross_profit": 441259.0,
   "net_income": 168581.0,
   "net_income_ttm": 644309.0,
   "net_income_yoy": 40.29,
   "net_margin": 38.2,
   "operating_expenses": 243913.0,
   "operating_income": 197346.0,
   "operating_income_yoy": 41.78,
   "operating_income_yoy_accel": -10.5,
   "operating_margin": 44.72,
   "pretax_income": 198974.0,
   "revenue": 441259.0,
   "revenue_ttm": 1641867.0,
   "revenue_yoy": 31.1,
   "revenue_yoy_accel": -2.62,
   "roa_q": 7.61,
   "roa_ttm": 29.1,
   "roe_q": 9.44,
   "roe_ttm": 36.09,
   "total_assets": 2214082.0,
   "total_liabilities": 428625.0
  },
  "2020Q4": {
   "cogs": 0.0,
   "current_assets": 1898915.0,
   "current_liabilities": 448093.0,
   "current_ratio": 423.78,
   "debt_ratio": 19.05,
   "eps": 2.6,
   "eps_ttm": 9.52,
   "eps_yoy": 49.43,
   "equity": 2005643.0,
   "equity_parent": 1996271.0,
   "gross_margin": 100.0,
   "gross_profit": 496682.0,
   "net_income": 192189.0,
   "net_income_ttm": 706845.0,
   "net_income_yoy": 48.23,
   "net_margin": 38.69,
   "operating_expenses": 261327.0,
   "operating_income": 235355.0,
   "operating_income_yoy": 47.55,
   "operating_income_yoy_accel": 5.77,
   "operating_margin": 47.39,
   "pretax_income": 230733.0,
   "revenue": 496682.0,
   "revenue_ttm": 1776653.0,
   "revenue_yoy": 37.24,
   "revenue_yoy_accel": 6.14,
   "roa_q": 7.76,
   "roa_ttm": 28.53,
   "roe_q": 9.58,
   "roe_ttm": 35.24,
   "total_assets": 2477572.0,
   "total_liabilities": 471929.0
  },
  "2021Q1": {
   "cogs": 0.0,
   "current_assets": 2249431.0,
   "current_liabilities": 495699.0,
   "current_ratio": 453.79,
   "debt_ratio": 18.45,
   "eps": 3.93,
   "eps_ttm": 11.07,
   "eps_yoy": 65.13,
   "equity": 2303462.0,
   "equity_parent": 2295615.0,
   "gross_margin": 100.0,
   "gross_profit": 596734.0,
   "net_income": 291434.0,
   "net_income_ttm": 821521.0,
   "net_income_yoy": 64.88,
   "net_margin": 48.84,
   "operating_expenses": 259023.0,
   "operating_income": 337711.0,
   "operating_income_yoy": 74.1,
   "operating_income_yoy_accel": 26.55,
   "operating_margin": 56.59,
   "pretax_income": 344341.0,
   "revenue": 596734.0,
   "revenue_ttm": 1957951.0,
   "revenue_yoy": 43.64,
   "revenue_yoy_accel": 6.4,
   "roa_q": 10.32,
   "roa_ttm": 29.08,
   "roe_q": 12.65,
   "roe_ttm": 35.66,
   "total_assets": 2824558.0,
   "total_liabilities": 521096.0
  },
  "2021Q2": {
   "cogs": 0.0,
   "current_assets": 2535240.0,
   "current_liabilities": 1176296.0,
   "current_ratio": 215.53,
   "debt_ratio": 38.79,
   "eps": 3.27,
   "eps_ttm": 12.06,
   "eps_yoy": 43.42,
   "equity": 1895206.0,
   "equity_parent": 1889027.0,
   "gross_margin": 100.0,
   "gross_profit": 541415.0,
   "net_income": 241910.0,
   "net_income_ttm": 894114.0,
   "net_income_yoy": 42.87,
   "net_margin": 44.68,
   "operating_expenses": 258701.0,
   "operating_income": 282714.0,
   "operating_income_yoy": 44.31,
   "operating_income_yoy_accel": -29.79,
   "operating_margin": 52.22,
   "pretax_income": 283150.0,
   "revenue": 541415.0,
   "revenue_ttm": 2076090.0,
   "revenue_yoy": 27.91,
   "revenue_yoy_accel": -15.73,
   "roa_q": 7.81,
   "roa_ttm": 28.88,
   "roe_q": 12.76,
   "roe_ttm": 47.18,
   "total_assets": 3096314.0,
   "total_liabilities": 1201108.0
  },
  "2021Q3": {
   "cogs": 0.0,
   "current_assets": 2170194.0,
   "current_liabilities": 525307.0,
   "current_ratio": 413.13,
   "debt_ratio": 20.18,
   "eps": 3.72,
   "eps_ttm": 13.52,
   "eps_yoy": 64.6,
   "equity": 2175108.0,
   "equity_parent": 2169811.0,
   "gross_margin": 100.0,
   "gross_profit": 594277.0,
   "net_income": 275153.0,
   "net_income_ttm": 1000686.0,
   "net_income_yoy": 63.22,
   "net_margin": 46.3,
   "operating_expenses": 277611.0,
   "operating_income": 316666.0,
   "operating_income_yoy": 60.46,
   "operating_income_yoy_accel": 16.15,
   "operating_margin": 53.29,
   "pretax_income": 323101.0,
   "revenue": 594277.0,
   "revenue_ttm": 2229108.0,
   "revenue_yoy": 34.68,
   "revenue_yoy_accel": 6.77,
   "roa_q": 10.1,
   "roa_ttm": 36.72,
   "roe_q": 12.65,
   "roe_ttm": 46.01,
   "total_assets": 2725103.0,
   "total_liabilities": 549995.0
  },
  "2021Q4": {
   "cogs": 0.0,
   "current_assets": 2621819.0,
   "current_liabilities": 639785.0,
   "current_ratio": 409.8,
   "debt_ratio": 20.85,
   "eps": 3.86,
   "eps_ttm": 14.78,
   "eps_yoy": 48.46,
   "equity": 2522791.0,
   "equity_parent": 2475376.0,
   "gross_margin": 100.0,
   "gross_profit": 631398.0,
   "net_income": 285157.0,
   "net_income_ttm": 1093654.0,
   "net_income_yoy": 48.37,
   "net_margin": 45.16,
   "operating_expenses": 299677.0,
   "operating_income": 331721.0,
   "operating_income_yoy": 40.94,
   "operating_income_yoy_accel": -19.52,
   "operating_margin": 52.54,
   "pretax_income": 332506.0,
   "revenue": 631398.0,
   "revenue_ttm": 2363824.0,
   "revenue_yoy": 27.12,
   "revenue_yoy_accel": -7.56,
   "roa_q": 8.95,
   "roa_ttm": 34.31,
   "roe_q": 11.3,
   "roe_ttm": 43.35,
   "total_assets": 3187308.0,
   "total_liabilities": 664517.0
  },
  "2022Q1": {
   "cogs": 0.0,
   "current_assets": 3072049.0,
   "current_liabilities": 719793.0,
   "current_ratio": 426.8,
   "debt_ratio": 20.5,
   "eps": 4.91,
   "eps_ttm": 15.76,
   "eps_yoy": 24.94,
   "equity": 2884071.0,
   "equity_parent": 2848526.0,
   "gross_margin": 100.0,
   "gross_profit": 727107.0,
   "net_income": 362238.0,
   "net_income_ttm": 1164458.0,
   "net_income_yoy": 24.3,
   "net_margin": 49.82,
   "operating_expenses": 313846.0,
   "operating_income": 413261.0,
   "operating_income_yoy": 22.37,
   "operating_income_yoy_accel": -18.57,
   "operating_margin": 56.84,
   "pretax_income": 428101.0,
   "revenue": 727107.0,
   "revenue_ttm": 2494197.0,
   "revenue_yoy": 21.85,
   "revenue_yoy_accel": -5.27,
   "roa_q": 9.99,
   "roa_ttm": 32.1,
   "roe_q": 12.56,
   "roe_ttm": 40.38,
   "total_assets": 3627590.0,
   "total_liabilities": 743519.0
  },
  "2022Q2": {
   "cogs": 0.0,
   "current_assets": 3476090.0,
   "current_liabilities": 1781253.0,
   "current_ratio": 195.15,
   "debt_ratio": 44.33,
   "eps": 5.48,
   "eps_ttm": 17.97,
   "eps_yoy": 67.58,
   "equity": 2265629.0,
   "equity_parent": 2228942.0,
   "gross_margin": 100.0,
   "gross_profit": 796292.0,
   "net_income": 409741.0,
   "net_income_ttm": 1332289.0,
   "net_income_yoy": 69.38,
   "net_margin": 51.46,
   "operating_expenses": 336197.0,
   "operating_income": 460095.0,
   "operating_income_yoy": 62.74,
   "operating_income_yoy_accel": 40.37,
   "operating_margin": 57.78,
   "pretax_income": 475320.0,
   "revenue": 796292.0,
   "revenue_ttm": 2749074.0,
   "revenue_yoy": 47.08,
   "revenue_yoy_accel": 25.23,
   "roa_q": 10.07,
   "roa_ttm": 32.74,
   "roe_q": 18.09,
   "roe_ttm": 58.8,
   "total_assets": 4069591.0,
   "total_liabilities": 1803962.0
  },
  "2022Q3": {
   "cogs": 0.0,
   "current_assets": 2759060.0,
   "current_liabilities": 650520.0,
   "current_ratio": 424.13,
   "debt_ratio": 20.25,
   "eps": 5.45,
   "eps_ttm": 19.7,
   "eps_yoy": 46.51,
   "equity": 2653835.0,
   "equity_parent": 2629991.0,
   "gross_margin": 100.0,
   "gross_profit": 790608.0,
   "net_income": 402056.0,
   "net_income_ttm": 1459192.0,
   "net_income_yoy": 46.12,
   "net_margin": 50.85,
   "operating_expenses": 345160.0,
   "operating_income": 445448.0,
   "operating_income_yoy": 40.67,
   "operating_income_yoy_accel": -22.07,
   "operating_margin": 56.34,
   "pretax_income": 485456.0,
   "revenue": 790608.0,
   "revenue_ttm": 2945405.0,
   "revenue_yoy": 33.04,
   "revenue_yoy_accel": -14.04,
   "roa_q": 12.08,
   "roa_ttm": 43.85,
   "roe_q": 15.15,
   "roe_ttm": 54.98,
   "total_assets": 3327522.0,
   "total_liabilities": 673687.0
  },
  "2022Q4": {
   "cogs": 0.0,
   "eps": 5.77,
   "eps_ttm": 21.61,
   "eps_yoy": 49.48,
   "gross_margin": 100.0,
   "gross_profit": 902704.0,
   "net_income": 430106.0,
   "net_income_ttm": 1604141.0,
   "net_income_yoy": 50.83,
   "net_margin": 47.65,
   "operating_expenses": 368090.0,
   "operating_income": 534614.0,
   "operating_income_yoy": 61.16,
   "operating_income_yoy_accel": 20.49,
   "operating_margin": 59.22,
   "pretax_income": 520047.0,
   "revenue": 902704.0,
   "revenue_ttm": 3216711.0,
   "revenue_yoy": 42.97,
   "revenue_yoy_accel": 9.93
  },
  "2023Q1": {
   "cogs": 0.0,
   "current_assets": 3639234.0,
   "current_liabilities": 792862.0,
   "current_ratio": 459.0,
   "debt_ratio": 19.18,
   "eps": 4.2,
   "eps_ttm": 20.9,
   "eps_yoy": -14.46,
   "equity": 3414339.0,
   "equity_parent": 3374776.0,
   "gross_margin": 100.0,
   "gross_profit": 667751.0,
   "net_income": 307558.0,
   "net_income_ttm": 1549461.0,
   "net_income_yoy": -15.1,
   "net_margin": 46.06,
   "operating_expenses": 300657.0,
   "operating_income": 367094.0,
   "operating_income_yoy": -11.17,
   "operating_income_yoy_accel": -72.33,
   "operating_margin": 54.97,
   "pretax_income": 371530.0,
   "revenue": 667751.0,
   "revenue_ttm": 3157355.0,
   "revenue_yoy": -8.16,
   "revenue_yoy_accel": -51.13,
   "roa_q": 7.28,
   "roa_ttm": 36.68,
   "roe_q": 9.01,
   "roe_ttm": 45.38,
   "total_assets": 4224523.0,
   "total_liabilities": 810184.0
  },
  "2023Q2": {
   "cogs": 0.0,
   "current_assets": 4014724.0,
   "current_liabilities": 2353000.0,
   "current_ratio": 170.62,
   "debt_ratio": 51.45,
   "eps": 4.71,
   "eps_ttm": 20.13,
   "eps_yoy": -14.05,
   "equity": 2237328.0,
   "equity_parent": 2203203.0,
   "gross_margin": 100.0,
   "gross_profit": 696625.0,
   "net_income": 349778.0,
   "net_income_ttm": 1489498.0,
   "net_income_yoy": -14.63,
   "net_margin": 50.21,
   "operating_expenses": 327865.0,
   "operating_income": 368760.0,
   "operating_income_yoy": -19.85,
   "operating_income_yoy_accel": -8.68,
   "operating_margin": 52.94,
   "pretax_income": 415861.0,
   "revenue": 696625.0,
   "revenue_ttm": 3057688.0,
   "revenue_yoy": -12.52,
   "revenue_yoy_accel": -4.36,
   "roa_q": 7.59,
   "roa_ttm": 32.32,
   "roe_q": 15.63,
   "roe_ttm": 66.57,
   "total_assets": 4607987.0,
   "total_liabilities": 2370659.0
  },
  "2023Q3": {
   "cogs": 0.0,
   "eps": 5.44,
   "eps_ttm": 20.12,
   "eps_yoy": -0.18,
   "gross_margin": 100.0,
   "gross_profit": 787091.0,
   "net_income": 405703.0,
   "net_income_ttm": 1493145.0,
   "net_income_yoy": 0.91,
   "net_margin": 51.54,
   "operating_expenses": 369873.0,
   "operating_income": 417218.0,
   "operating_income_yoy": -6.34,
   "operating_income_yoy_accel": 13.51,
   "operating_margin": 53.01,
   "pretax_income": 486233.0,
   "revenue": 787091.0,
   "revenue_ttm": 3054171.0,
   "revenue_yoy": -0.44,
   "revenue_yoy_accel": 12.08
  },
  "2023Q4": {
   "cogs": 0.0,
   "eps": 5.41,
   "eps_ttm": 19.76,
   "eps_yoy": -6.24,
   "gross_margin": 100.0,
   "gross_profit": 898858.0,
   "net_income": 399618.0,
   "net_income_ttm": 1462657.0,
   "net_income_yoy": -7.09,
   "net_margin": 44.46,
   "operating_expenses": 359330.0,
   "operating_income": 539528.0,
   "operating_income_yoy": 0.92,
   "operating_income_yoy_accel": 7.26,
   "operating_margin": 60.02,
   "pretax_income": 477368.0,
   "revenue": 898858.0,
   "revenue_ttm": 3050325.0,
   "revenue_yoy": -0.43,
   "revenue_yoy_accel": 0.01
  },
  "2024Q1": {
   "cogs": 0.0,
   "eps": 5.77,
   "eps_ttm": 21.33,
   "eps_yoy": 37.38,
   "gross_margin": 100.0,
   "gross_profit": 802764.0,
   "net_income": 423055.0,
   "net_income_ttm": 1578154.0,
   "net_income_yoy": 37.55,
   "net_margin": 52.7,
   "operating_expenses": 382143.0,
   "operating_income": 420621.0,
   "operating_income_yoy": 14.58,
   "operating_income_yoy_accel": 13.66,
   "operating_margin": 52.4,
   "pretax_income": 511499.0,
   "revenue": 802764.0,
   "revenue_ttm": 3185338.0,
   "revenue_yoy": 20.22,
   "revenue_yoy_accel": 20.65
  },
  "2024Q2": {
   "cogs": 0.0,
   "eps": 6.36,
   "eps_ttm": 22.98,
   "eps_yoy": 35.03,
   "gross_margin": 100.0,
   "gross_profit": 893010.0,
   "net_income": 473142.0,
   "net_income_ttm": 1701518.0,
   "net_income_yoy": 35.27,
   "net_margin": 52.98,
   "operating_expenses": 397829.0,
   "operating_income": 495181.0,
   "operating_income_yoy": 34.28,
   "operating_income_yoy_accel": 19.7,
   "operating_margin": 55.45,
   "pretax_income": 536177.0,
   "revenue": 893010.0,
   "revenue_ttm": 3381723.0,
   "revenue_yoy": 28.19,
   "revenue_yoy_accel": 7.97
  },
  "2024Q3": {
   "cogs": 0.0,
   "current_assets": 2972171.0,
   "current_liabilities": 721713.0,
   "current_ratio": 411.82,
   "debt_ratio": 19.42,
   "eps": 5.54,
   "eps_ttm": 23.08,
   "eps_yoy": 1.84,
   "equity": 3061866.0,
   "equity_parent": 3043743.0,
   "gross_margin": 100.0,
   "gross_profit": 899477.0,
   "net_income": 409565.0,
   "net_income_ttm": 1705380.0,
   "net_income_yoy": 0.95,
   "net_margin": 45.53,
   "operating_expenses": 394561.0,
   "operating_income": 504916.0,
   "operating_income_yoy": 21.02,
   "operating_income_yoy_accel": -13.26,
   "operating_margin": 56.13,
   "pretax_income": 489122.0,
   "revenue": 899477.0,
   "revenue_ttm": 3494109.0,
   "revenue_yoy": 14.28,
   "revenue_yoy_accel": -13.91,
   "roa_q": 10.78,
   "roa_ttm": 44.88,
   "roe_q": 13.38,
   "roe_ttm": 55.7,
   "total_assets": 3799939.0,
   "total_liabilities": 738073.0
  },
  "2024Q4": {
   "cogs": 0.0,
   "current_assets": 3636784.0,
   "current_liabilities": 859903.0,
   "current_ratio": 422.93,
   "debt_ratio": 19.6,
   "eps": 6.89,
   "eps_ttm": 24.56,
   "eps_yoy": 27.36,
   "equity": 3584679.0,
   "equity_parent": 3564207.0,
   "gross_margin": 100.0,
   "gross_profit": 1010717.0,
   "net_income": 516496.0,
   "net_income_ttm": 1822258.0,
   "net_income_yoy": 29.25,
   "net_margin": 51.1,
   "operating_expenses": 444784.0,
   "operating_income": 565933.0,
   "operating_income_yoy": 4.89,
   "operating_income_yoy_accel": -16.13,
   "operating_margin": 55.99,
   "pretax_income": 617835.0,
   "revenue": 1010717.0,
   "revenue_ttm": 3605968.0,
   "revenue_yoy": 12.44,
   "revenue_yoy_accel": -1.84,
   "roa_q": 11.58,
   "roa_ttm": 40.87,
   "roe_q": 14.41,
   "roe_ttm": 50.83,
   "total_assets": 4458552.0,
   "total_liabilities": 873873.0
  },
  "2025Q1": {
   "cogs": 0.0,
   "current_assets": 4100625.0,
   "current_liabilities": 940382.0,
   "current_ratio": 436.06,
   "debt_ratio": 19.09,
   "eps": 6.18,
   "eps_ttm": 24.97,
   "eps_yoy": 7.11,
   "equity": 4039988.0,
   "equity_parent": 4026835.0,
   "gross_margin": 100.0,
   "gross_profit": 911734.0,
   "net_income": 453951.0,
   "net_income_ttm": 1853154.0,
   "net_income_yoy": 7.3,
   "net_margin": 49.79,
   "operating_expenses": 389387.0,
   "operating_income": 522347.0,
   "operating_income_yoy": 24.18,
   "operating_income_yoy_accel": 19.29,
   "operating_margin": 57.29,
   "pretax_income": 549926.0,
   "revenue": 911734.0,
   "revenue_ttm": 3714938.0,
   "revenue_yoy": 13.57,
   "revenue_yoy_accel": 1.13,
   "roa_q": 9.09,
   "roa_ttm": 37.11,
   "roe_q": 11.24,
   "roe_ttm": 45.87,
   "total_assets": 4993145.0,
   "total_liabilities": 953157.0
  },
  "2025Q2": {
   "cogs": 0.0,
   "current_assets": 4566513.0,
   "current_liabilities": 2688789.0,
   "current_ratio": 169.84,
   "debt_ratio": 49.12,
   "eps": 5.36,
   "eps_ttm": 23.97,
   "eps_yoy": -15.72,
   "equity": 2796730.0,
   "equity_parent": 2785450.0,
   "gross_margin": 100.0,
   "gross_profit": 936535.0,
   "net_income": 397890.0,
   "net_income_ttm": 1777902.0,
   "net_income_yoy": -15.9,
   "net_margin": 42.49,
   "operating_expenses": 390644.0,
   "operating_income": 545891.0,
   "operating_income_yoy": 10.24,
   "operating_income_yoy_accel": -13.94,
   "operating_margin": 58.29,
   "pretax_income": 472288.0,
   "revenue": 936535.0,
   "revenue_ttm": 3758463.0,
   "revenue_yoy": 4.87,
   "revenue_yoy_accel": -8.7,
   "roa_q": 7.24,
   "roa_ttm": 32.34,
   "roe_q": 14.23,
   "roe_ttm": 63.57,
   "total_assets": 5496945.0,
   "total_liabilities": 2700215.0
  },
  "2025Q3": {
   "cogs": 0.0,
   "current_assets": 3084404.0,
   "current_liabilities": 765031.0,
   "current_ratio": 403.17,
   "debt_ratio": 19.08,
   "eps": 6.52,
   "eps_ttm": 24.95,
   "eps_yoy": 17.69,
   "equity": 3291086.0,
   "equity_parent": 3277839.0,
   "gross_margin": 100.0,
   "gross_profit": 952422.0,
   "net_income": 488442.0,
   "net_income_ttm": 1856779.0,
   "net_income_yoy": 19.26,
   "net_margin": 51.28,
   "operating_expenses": 404068.0,
   "operating_income": 548354.0,
   "operating_income_yoy": 8.6,
   "operating_income_yoy_accel": -1.64,
   "operating_margin": 57.57,
   "pretax_income": 581821.0,
   "revenue": 952422.0,
   "revenue_ttm": 3811408.0,
   "revenue_yoy": 5.89,
   "revenue_yoy_accel": 1.02,
   "roa_q": 12.01,
   "roa_ttm": 45.65,
   "roe_q": 14.84,
   "roe_ttm": 56.42,
   "total_assets": 4067011.0,
   "total_liabilities": 775925.0
  },
  "2025Q4": {
   "cogs": 0.0,
   "current_assets": 3801219.0,
   "current_liabilities": 879922.0,
   "current_ratio": 431.99,
   "debt_ratio": 18.68,
   "eps": 7.54,
   "eps_ttm": 25.6,
   "eps_yoy": 9.43,
   "equity": 3871374.0,
   "equity_parent": 3841865.0,
   "gross_margin": 100.0,
   "gross_profit": 1048362.0,
   "net_income": 578330.0,
   "net_income_ttm": 1918613.0,
   "net_income_yoy": 11.97,
   "net_margin": 55.17,
   "operating_expenses": 412617.0,
   "operating_income": 635745.0,
   "operating_income_yoy": 12.34,
   "operating_income_yoy_accel": 3.74,
   "operating_margin": 60.64,
   "pretax_income": 680495.0,
   "revenue": 1048362.0,
   "revenue_ttm": 3849053.0,
   "revenue_yoy": 3.72,
   "revenue_yoy_accel": -2.17,
   "roa_q": 12.15,
   "roa_ttm": 40.3,
   "roe_q": 14.94,
   "roe_ttm": 49.56,
   "total_assets": 4760570.0,
   "total_liabilities": 889196.0
  },
  "2026Q1": {
   "cogs": 0.0,
   "current_assets": 4568062.0,
   "current_liabilities": 1083025.0,
   "current_ratio": 421.79,
   "eps": 7.98,
   "eps_ttm": 27.4,
   "eps_yoy": 29.13,
   "equity_parent": 4438987.0,
   "gross_margin": 100.0,
   "gross_profit": 1093993.0,
   "net_income": 615751.0,
   "net_income_ttm": 2080413.0,
   "net_income_yoy": 35.64,
   "net_margin": 56.28,
   "operating_expenses": 431616.0,
   "operating_income": 662377.0,
   "operating_income_yoy": 26.81,
   "operating_income_yoy_accel": 14.47,
   "operating_margin": 60.55,
   "pretax_income": 695451.0,
   "revenue": 1093993.0,
   "revenue_ttm": 4031312.0,
   "revenue_yoy": 19.99,
   "revenue_yoy_accel": 16.27
  }
 },
 "sector": "IP/ASIC",
 "sector_parent": "電子上游"
}