{
 "code": "6432",
 "industry": "電子零組件業",
 "monthly": {
  "2014-12": {
   "revenue": 77948.0
  },
  "2015-01": {
   "mom": 21.3,
   "revenue": 94548.0
  },
  "2015-02": {
   "mom": -43.23,
   "revenue": 53673.0
  },
  "2015-03": {
   "mom": 46.37,
   "revenue": 78563.0
  },
  "2015-04": {
   "mom": 18.55,
   "revenue": 93138.0
  },
  "2015-05": {
   "mom": -22.92,
   "revenue": 71794.0
  },
  "2015-06": {
   "mom": 4.89,
   "revenue": 75302.0
  },
  "2015-07": {
   "mom": 7.09,
   "revenue": 80638.0
  },
  "2015-08": {
   "mom": 11.01,
   "revenue": 89517.0
  },
  "2015-09": {
   "mom": 4.42,
   "revenue": 93478.0
  },
  "2015-10": {
   "mom": -17.01,
   "revenue": 77573.0
  },
  "2015-11": {
   "mom": 15.56,
   "revenue": 89645.0
  },
  "2015-12": {
   "mom": -8.73,
   "revenue": 81819.0,
   "yoy": 4.97
  },
  "2016-01": {
   "mom": 31.04,
   "revenue": 107219.0,
   "yoy": 13.4
  },
  "2016-02": {
   "mom": -49.3,
   "revenue": 54356.0,
   "yoy": 1.27
  },
  "2016-03": {
   "mom": 36.15,
   "revenue": 74003.0,
   "yoy": -5.8
  },
  "2016-04": {
   "mom": 0.94,
   "revenue": 74699.0,
   "yoy": -19.8
  },
  "2016-05": {
   "mom": 6.48,
   "revenue": 79543.0,
   "yoy": 10.79
  },
  "2016-06": {
   "mom": 4.46,
   "revenue": 83094.0,
   "yoy": 10.35
  },
  "2016-07": {
   "mom": 1.39,
   "revenue": 84251.0,
   "yoy": 4.48
  },
  "2016-08": {
   "mom": -4.98,
   "revenue": 80054.0,
   "yoy": -10.57
  },
  "2016-09": {
   "mom": 4.16,
   "revenue": 83387.0,
   "yoy": -10.8
  },
  "2016-10": {
   "mom": -7.84,
   "revenue": 76852.0,
   "yoy": -0.93
  },
  "2016-11": {
   "mom": 0.1,
   "revenue": 76931.0,
   "yoy": -14.18
  },
  "2016-12": {
   "mom": 7.06,
   "revenue": 82360.0,
   "yoy": 0.66
  },
  "2017-01": {
   "mom": -20.85,
   "revenue": 65188.0,
   "yoy": -39.2
  },
  "2017-02": {
   "mom": -14.49,
   "revenue": 55741.0,
   "yoy": 2.55
  },
  "2017-03": {
   "mom": 34.17,
   "revenue": 74790.0,
   "yoy": 1.06
  },
  "2017-04": {
   "mom": -5.84,
   "revenue": 70420.0,
   "yoy": -5.73
  },
  "2017-05": {
   "mom": -9.6,
   "revenue": 63662.0,
   "yoy": -19.97
  },
  "2017-06": {
   "mom": 11.63,
   "revenue": 71066.0,
   "yoy": -14.48
  },
  "2017-07": {
   "mom": -2.58,
   "revenue": 69230.0,
   "yoy": -17.83
  },
  "2017-08": {
   "mom": 8.8,
   "revenue": 75325.0,
   "yoy": -5.91
  },
  "2017-09": {
   "mom": 7.67,
   "revenue": 81100.0,
   "yoy": -2.74
  },
  "2017-10": {
   "mom": -24.14,
   "revenue": 61524.0,
   "yoy": -19.94
  },
  "2017-11": {
   "mom": 37.83,
   "revenue": 84799.0,
   "yoy": 10.23
  },
  "2017-12": {
   "mom": -13.59,
   "revenue": 73279.0,
   "yoy": -11.03
  },
  "2018-01": {
   "mom": 12.17,
   "revenue": 82198.0,
   "yoy": 26.09
  },
  "2018-02": {
   "mom": -19.14,
   "revenue": 66466.0,
   "yoy": 19.24
  },
  "2018-03": {
   "mom": 20.18,
   "revenue": 79877.0,
   "yoy": 6.8
  },
  "2018-04": {
   "mom": -5.81,
   "revenue": 75239.0,
   "yoy": 6.84
  },
  "2018-05": {
   "mom": 8.85,
   "revenue": 81898.0,
   "yoy": 28.65
  },
  "2018-06": {
   "mom": -1.45,
   "revenue": 80713.0,
   "yoy": 13.57
  },
  "2018-07": {
   "mom": -7.16,
   "revenue": 74932.0,
   "yoy": 8.24
  },
  "2018-08": {
   "mom": 26.25,
   "revenue": 94603.0,
   "yoy": 25.59
  },
  "2018-09": {
   "mom": -11.84,
   "revenue": 83403.0,
   "yoy": 2.84
  },
  "2018-10": {
   "mom": -5.82,
   "revenue": 78552.0,
   "yoy": 27.68
  },
  "2018-11": {
   "mom": -3.86,
   "revenue": 75520.0,
   "yoy": -10.94
  },
  "2018-12": {
   "mom": -10.59,
   "revenue": 67520.0,
   "yoy": -7.86
  },
  "2019-01": {
   "mom": 15.99,
   "revenue": 78317.0,
   "yoy": -4.72
  },
  "2019-02": {
   "mom": -24.19,
   "revenue": 59374.0,
   "yoy": -10.67
  },
  "2019-03": {
   "mom": 28.19,
   "revenue": 76109.0,
   "yoy": -4.72
  },
  "2019-04": {
   "mom": 2.38,
   "revenue": 77921.0,
   "yoy": 3.56
  },
  "2019-05": {
   "mom": 4.42,
   "revenue": 81362.0,
   "yoy": -0.65
  },
  "2019-06": {
   "mom": -14.05,
   "revenue": 69928.0,
   "yoy": -13.36
  },
  "2019-07": {
   "mom": 10.03,
   "revenue": 76940.0,
   "yoy": 2.68
  },
  "2019-08": {
   "mom": -0.76,
   "revenue": 76358.0,
   "yoy": -19.29
  },
  "2019-09": {
   "mom": 9.04,
   "revenue": 83259.0,
   "yoy": -0.17
  },
  "2019-10": {
   "mom": -11.61,
   "revenue": 73591.0,
   "yoy": -6.32
  },
  "2019-11": {
   "mom": 16.66,
   "revenue": 85854.0,
   "yoy": 13.68
  },
  "2019-12": {
   "mom": -6.09,
   "revenue": 80625.0,
   "yoy": 19.41
  },
  "2020-01": {
   "mom": 7.01,
   "revenue": 86274.0,
   "yoy": 10.16
  },
  "2020-02": {
   "mom": -33.55,
   "revenue": 57328.0,
   "yoy": -3.45
  },
  "2020-03": {
   "mom": 47.55,
   "revenue": 84589.0,
   "yoy": 11.14
  },
  "2020-04": {
   "mom": 8.79,
   "revenue": 92023.0,
   "yoy": 18.1
  },
  "2020-05": {
   "mom": -2.0,
   "revenue": 90186.0,
   "yoy": 10.85
  },
  "2020-06": {
   "mom": -0.12,
   "revenue": 90074.0,
   "yoy": 28.81
  },
  "2020-07": {
   "mom": 8.91,
   "revenue": 98100.0,
   "yoy": 27.5
  },
  "2020-08": {
   "mom": -6.29,
   "revenue": 91927.0,
   "yoy": 20.39
  },
  "2020-09": {
   "mom": 23.13,
   "revenue": 113187.0,
   "yoy": 35.95
  },
  "2020-10": {
   "mom": -20.41,
   "revenue": 90086.0,
   "yoy": 22.41
  },
  "2020-11": {
   "mom": 8.31,
   "revenue": 97572.0,
   "yoy": 13.65
  },
  "2020-12": {
   "mom": 8.01,
   "revenue": 105391.0,
   "yoy": 30.72
  },
  "2021-01": {
   "mom": 15.88,
   "revenue": 122131.0,
   "yoy": 41.56
  },
  "2021-02": {
   "mom": -34.52,
   "revenue": 79969.0,
   "yoy": 39.49
  },
  "2021-03": {
   "mom": 29.75,
   "revenue": 103762.0,
   "yoy": 22.67
  },
  "2021-04": {
   "mom": 33.01,
   "revenue": 138012.0,
   "yoy": 49.98
  },
  "2021-05": {
   "mom": -8.01,
   "revenue": 126952.0,
   "yoy": 40.77
  },
  "2021-06": {
   "mom": -7.54,
   "revenue": 117380.0,
   "yoy": 30.32
  },
  "2021-07": {
   "mom": 4.59,
   "revenue": 122772.0,
   "yoy": 25.15
  },
  "2021-08": {
   "mom": -16.49,
   "revenue": 102532.0,
   "yoy": 11.54
  },
  "2021-09": {
   "mom": 12.45,
   "revenue": 115295.0,
   "yoy": 1.86
  },
  "2021-10": {
   "mom": -8.98,
   "revenue": 104936.0,
   "yoy": 16.48
  },
  "2021-11": {
   "mom": 5.59,
   "revenue": 110797.0,
   "yoy": 13.55
  },
  "2021-12": {
   "mom": 8.36,
   "revenue": 120061.0,
   "yoy": 13.92
  },
  "2022-01": {
   "mom": 19.78,
   "revenue": 143805.0,
   "yoy": 17.75
  },
  "2022-02": {
   "mom": -32.28,
   "revenue": 97383.0,
   "yoy": 21.78
  },
  "2022-03": {
   "mom": 20.13,
   "revenue": 116991.0,
   "yoy": 12.75
  },
  "2022-04": {
   "mom": -6.88,
   "revenue": 108938.0,
   "yoy": -21.07
  },
  "2022-05": {
   "mom": -14.55,
   "revenue": 93083.0,
   "yoy": -26.68
  },
  "2022-06": {
   "mom": -13.77,
   "revenue": 80267.0,
   "yoy": -31.62
  },
  "2022-07": {
   "mom": -2.46,
   "revenue": 78290.0,
   "yoy": -36.23
  },
  "2022-08": {
   "mom": -1.74,
   "revenue": 76925.0,
   "yoy": -24.97
  },
  "2022-09": {
   "mom": 7.5,
   "revenue": 82693.0,
   "yoy": -28.28
  },
  "2022-10": {
   "mom": -14.41,
   "revenue": 70778.0,
   "yoy": -32.55
  },
  "2022-11": {
   "mom": 27.51,
   "revenue": 90252.0,
   "yoy": -18.54
  },
  "2022-12": {
   "mom": -17.58,
   "revenue": 74389.0,
   "yoy": -38.04
  },
  "2023-01": {
   "mom": 1.87,
   "revenue": 75777.0,
   "yoy": -47.31
  },
  "2023-02": {
   "mom": 2.04,
   "revenue": 77323.0,
   "yoy": -20.6
  },
  "2023-03": {
   "mom": 21.86,
   "revenue": 94225.0,
   "yoy": -19.46
  },
  "2023-04": {
   "mom": -5.73,
   "revenue": 88822.0,
   "yoy": -18.47
  },
  "2023-05": {
   "mom": -3.95,
   "revenue": 85310.0,
   "yoy": -8.35
  },
  "2023-06": {
   "mom": 7.38,
   "revenue": 91608.0,
   "yoy": 14.13
  },
  "2023-07": {
   "mom": 16.23,
   "revenue": 106476.0,
   "yoy": 36.0
  },
  "2023-08": {
   "mom": 4.32,
   "revenue": 111080.0,
   "yoy": 44.4
  },
  "2023-09": {
   "mom": 1.18,
   "revenue": 112386.0,
   "yoy": 35.91
  },
  "2023-10": {
   "mom": -32.85,
   "revenue": 75468.0,
   "yoy": 6.63
  },
  "2023-11": {
   "mom": 16.98,
   "revenue": 88282.0,
   "yoy": -2.18
  },
  "2023-12": {
   "mom": -16.42,
   "revenue": 73784.0,
   "yoy": -0.81
  },
  "2024-01": {
   "mom": 34.27,
   "revenue": 99071.0,
   "yoy": 30.74
  },
  "2024-02": {
   "mom": -44.99,
   "revenue": 54501.0,
   "yoy": -29.52
  },
  "2024-03": {
   "mom": 40.34,
   "revenue": 76485.0,
   "yoy": -18.83
  },
  "2024-04": {
   "mom": 18.35,
   "revenue": 90517.0,
   "yoy": 1.91
  },
  "2024-05": {
   "mom": 0.35,
   "revenue": 90832.0,
   "yoy": 6.47
  },
  "2024-06": {
   "mom": -6.31,
   "revenue": 85097.0,
   "yoy": -7.11
  },
  "2024-07": {
   "mom": 15.64,
   "revenue": 98406.0,
   "yoy": -7.58
  },
  "2024-08": {
   "mom": -5.44,
   "revenue": 93057.0,
   "yoy": -16.23
  },
  "2024-09": {
   "mom": -10.5,
   "revenue": 83289.0,
   "yoy": -25.89
  },
  "2024-10": {
   "mom": -5.91,
   "revenue": 78369.0,
   "yoy": 3.84
  },
  "2024-11": {
   "mom": 13.09,
   "revenue": 88624.0,
   "yoy": 0.39
  },
  "2024-12": {
   "mom": -7.82,
   "revenue": 81697.0,
   "yoy": 10.72
  },
  "2025-01": {
   "mom": 11.62,
   "revenue": 91188.0,
   "yoy": -7.96
  },
  "2025-02": {
   "mom": -9.32,
   "revenue": 82687.0,
   "yoy": 51.72
  },
  "2025-03": {
   "mom": 36.99,
   "revenue": 113275.0,
   "yoy": 48.1
  },
  "2025-04": {
   "mom": -4.65,
   "revenue": 108008.0,
   "yoy": 19.32
  },
  "2025-05": {
   "mom": -22.01,
   "revenue": 84231.0,
   "yoy": -7.27
  },
  "2025-06": {
   "mom": 0.06,
   "revenue": 84278.0,
   "yoy": -0.96
  },
  "2025-07": {
   "mom": 14.74,
   "revenue": 96697.0,
   "yoy": -1.74
  },
  "2025-08": {
   "mom": -3.94,
   "revenue": 92886.0,
   "yoy": -0.18
  },
  "2025-09": {
   "mom": 8.98,
   "revenue": 101226.0,
   "yoy": 21.54
  },
  "2025-10": {
   "mom": -17.35,
   "revenue": 83660.0,
   "yoy": 6.75
  },
  "2025-11": {
   "mom": -3.15,
   "revenue": 81026.0,
   "yoy": -8.57
  },
  "2025-12": {
   "mom": 30.59,
   "revenue": 105815.0,
   "yoy": 29.52
  },
  "2026-01": {
   "mom": 6.69,
   "revenue": 112898.0,
   "yoy": 23.81
  },
  "2026-02": {
   "mom": -34.23,
   "revenue": 74257.0,
   "yoy": -10.2
  },
  "2026-03": {
   "mom": 43.45,
   "revenue": 106524.0,
   "yoy": -5.96
  },
  "2026-04": {
   "mom": 6.87,
   "revenue": 113847.0,
   "yoy": 5.41
  },
  "2026-05": {
   "mom": -4.9,
   "revenue": 108274,
   "yoy": 28.54
  }
 },
 "name": "今展科",
 "quarterly": {
  "2015Q1": {
   "cogs": 170633.0,
   "current_assets": 546329.0,
   "current_liabilities": 274175.0,
   "current_ratio": 199.26,
   "debt_ratio": 44.45,
   "eps": 0.54,
   "equity": 346714.0,
   "equity_parent": 346714.0,
   "gross_margin": 24.76,
   "gross_profit": 56151.0,
   "net_income": 9082.0,
   "net_margin": 4.0,
   "operating_expenses": 44105.0,
   "operating_income": 12046.0,
   "operating_margin": 5.31,
   "pretax_income": 11388.0,
   "revenue": 226784.0,
   "roa_q": 1.45,
   "roe_q": 2.62,
   "total_assets": 624203.0,
   "total_liabilities": 277489.0
  },
  "2015Q2": {
   "cogs": 175152.0,
   "current_assets": 581435.0,
   "current_liabilities": 275283.0,
   "current_ratio": 211.21,
   "debt_ratio": 41.36,
   "eps": 0.59,
   "equity": 394925.0,
   "equity_parent": 394925.0,
   "gross_margin": 27.09,
   "gross_profit": 65081.0,
   "net_income": 10602.0,
   "net_margin": 4.41,
   "operating_expenses": 48219.0,
   "operating_income": 16862.0,
   "operating_margin": 7.02,
   "pretax_income": 14774.0,
   "revenue": 240233.0,
   "roa_q": 1.57,
   "roe_q": 2.68,
   "total_assets": 673522.0,
   "total_liabilities": 278597.0
  },
  "2015Q3": {
   "cogs": 195308.0,
   "current_assets": 635639.0,
   "current_liabilities": 287556.0,
   "current_ratio": 221.05,
   "debt_ratio": 40.22,
   "eps": 1.58,
   "equity": 432362.0,
   "equity_parent": 432362.0,
   "gross_margin": 25.92,
   "gross_profit": 68324.0,
   "net_income": 30177.0,
   "net_margin": 11.45,
   "operating_expenses": 48331.0,
   "operating_income": 19993.0,
   "operating_margin": 7.58,
   "pretax_income": 36510.0,
   "revenue": 263632.0,
   "roa_q": 4.17,
   "roe_q": 6.98,
   "total_assets": 723232.0,
   "total_liabilities": 290870.0
  },
  "2015Q4": {
   "cogs": 186327.0,
   "current_assets": 720648.0,
   "current_liabilities": 364243.0,
   "current_ratio": 197.85,
   "debt_ratio": 45.46,
   "eps": 0.71,
   "eps_ttm": 3.42,
   "equity": 440971.0,
   "equity_parent": 440971.0,
   "gross_margin": 25.18,
   "gross_profit": 62710.0,
   "net_income": 13831.0,
   "net_income_ttm": 63692.0,
   "net_margin": 5.55,
   "operating_expenses": 49641.0,
   "operating_income": 13069.0,
   "operating_margin": 5.25,
   "pretax_income": 14568.0,
   "revenue": 249037.0,
   "revenue_ttm": 979686.0,
   "roa_q": 1.71,
   "roa_ttm": 7.88,
   "roe_q": 3.14,
   "roe_ttm": 14.44,
   "total_assets": 808505.0,
   "total_liabilities": 367534.0
  },
  "2016Q1": {
   "cogs": 174027.0,
   "current_assets": 775212.0,
   "current_liabilities": 253879.0,
   "current_ratio": 305.35,
   "debt_ratio": 48.42,
   "eps": 0.52,
   "eps_ttm": 3.4,
   "eps_yoy": -3.7,
   "equity": 455431.0,
   "equity_parent": 455431.0,
   "gross_margin": 26.13,
   "gross_profit": 61551.0,
   "net_income": 10031.0,
   "net_income_ttm": 64641.0,
   "net_income_yoy": 10.45,
   "net_margin": 4.26,
   "operating_expenses": 45356.0,
   "operating_income": 16195.0,
   "operating_margin": 6.87,
   "pretax_income": 12124.0,
   "revenue": 235578.0,
   "revenue_ttm": 988480.0,
   "revenue_yoy": 3.88,
   "roa_q": 1.14,
   "roa_ttm": 7.32,
   "roe_q": 2.2,
   "roe_ttm": 14.19,
   "total_assets": 883044.0,
   "total_liabilities": 427613.0
  },
  "2016Q2": {
   "cogs": 176452.0,
   "current_assets": 734727.0,
   "current_liabilities": 257420.0,
   "current_ratio": 285.42,
   "debt_ratio": 51.08,
   "eps": 0.66,
   "eps_ttm": 3.47,
   "eps_yoy": 11.86,
   "equity": 413750.0,
   "equity_parent": 413750.0,
   "gross_margin": 25.65,
   "gross_profit": 60885.0,
   "net_income": 12766.0,
   "net_income_ttm": 66805.0,
   "net_income_yoy": 20.41,
   "net_margin": 5.38,
   "operating_expenses": 45607.0,
   "operating_income": 15278.0,
   "operating_margin": 6.44,
   "pretax_income": 16451.0,
   "revenue": 237337.0,
   "revenue_ttm": 985584.0,
   "revenue_yoy": -1.21,
   "roa_q": 1.51,
   "roa_ttm": 7.9,
   "roe_q": 3.09,
   "roe_ttm": 16.15,
   "total_assets": 845696.0,
   "total_liabilities": 431946.0
  },
  "2016Q3": {
   "cogs": 180724.0,
   "current_assets": 701531.0,
   "current_liabilities": 230333.0,
   "current_ratio": 304.57,
   "debt_ratio": 49.47,
   "eps": 0.38,
   "eps_ttm": 2.27,
   "eps_yoy": -75.95,
   "equity": 414380.0,
   "equity_parent": 414380.0,
   "gross_margin": 27.04,
   "gross_profit": 66969.0,
   "net_income": 7250.0,
   "net_income_ttm": 43878.0,
   "net_income_yoy": -75.98,
   "net_margin": 2.93,
   "operating_expenses": 41458.0,
   "operating_income": 25511.0,
   "operating_margin": 10.3,
   "pretax_income": 15848.0,
   "revenue": 247693.0,
   "revenue_ttm": 969645.0,
   "revenue_yoy": -6.05,
   "roa_q": 0.88,
   "roa_ttm": 5.35,
   "roe_q": 1.75,
   "roe_ttm": 10.59,
   "total_assets": 820044.0,
   "total_liabilities": 405664.0
  },
  "2016Q4": {
   "cogs": 184146.0,
   "eps": 0.45,
   "eps_ttm": 2.01,
   "eps_yoy": -36.62,
   "gross_margin": 22.02,
   "gross_profit": 51997.0,
   "net_income": 8767.0,
   "net_income_ttm": 38814.0,
   "net_income_yoy": -36.61,
   "net_margin": 3.71,
   "operating_expenses": 55281.0,
   "operating_income": -3284.0,
   "operating_margin": -1.39,
   "pretax_income": 9437.0,
   "revenue": 236143.0,
   "revenue_ttm": 956751.0,
   "revenue_yoy": -5.18
  },
  "2017Q1": {
   "cogs": 144941.0,
   "current_assets": 638796.0,
   "current_liabilities": 381934.0,
   "current_ratio": 167.25,
   "debt_ratio": 49.32,
   "eps": -0.74,
   "eps_ttm": 0.75,
   "eps_yoy": -242.31,
   "equity": 396049.0,
   "equity_parent": 396049.0,
   "gross_margin": 25.94,
   "gross_profit": 50778.0,
   "net_income": -14292.0,
   "net_income_ttm": 14491.0,
   "net_income_yoy": -242.48,
   "net_margin": -7.3,
   "operating_expenses": 45005.0,
   "operating_income": 5773.0,
   "operating_margin": 2.95,
   "pretax_income": -16624.0,
   "revenue": 195719.0,
   "revenue_ttm": 916892.0,
   "revenue_yoy": -16.92,
   "roa_q": -1.83,
   "roa_ttm": 1.85,
   "roe_q": -3.61,
   "roe_ttm": 3.66,
   "total_assets": 781425.0,
   "total_liabilities": 385376.0
  },
  "2017Q2": {
   "cogs": 150427.0,
   "current_assets": 709831.0,
   "current_liabilities": 462209.0,
   "current_ratio": 153.57,
   "debt_ratio": 54.5,
   "eps": 0.41,
   "eps_ttm": 0.5,
   "eps_yoy": -37.88,
   "equity": 388682.0,
   "equity_parent": 388682.0,
   "gross_margin": 26.67,
   "gross_profit": 54721.0,
   "net_income": 8200.0,
   "net_income_ttm": 9925.0,
   "net_income_yoy": -35.77,
   "net_margin": 4.0,
   "operating_expenses": 46264.0,
   "operating_income": 8457.0,
   "operating_margin": 4.12,
   "pretax_income": 9305.0,
   "revenue": 205148.0,
   "revenue_ttm": 884703.0,
   "revenue_yoy": -13.56,
   "roa_q": 0.96,
   "roa_ttm": 1.16,
   "roe_q": 2.11,
   "roe_ttm": 2.55,
   "total_assets": 854334.0,
   "total_liabilities": 465652.0
  },
  "2017Q3": {
   "cogs": 166850.0,
   "eps": 0.59,
   "eps_ttm": 0.71,
   "eps_yoy": 55.26,
   "gross_margin": 26.06,
   "gross_profit": 58805.0,
   "net_income": 11945.0,
   "net_income_ttm": 14620.0,
   "net_income_yoy": 64.76,
   "net_margin": 5.29,
   "operating_expenses": 47563.0,
   "operating_income": 11242.0,
   "operating_margin": 4.98,
   "pretax_income": 16779.0,
   "revenue": 225655.0,
   "revenue_ttm": 862665.0,
   "revenue_yoy": -8.9
  },
  "2017Q4": {
   "cogs": 165744.0,
   "eps": 0.15,
   "eps_ttm": 0.41,
   "eps_yoy": -66.67,
   "gross_margin": 24.53,
   "gross_profit": 53859.0,
   "net_income": 3052.0,
   "net_income_ttm": 8905.0,
   "net_income_yoy": -65.19,
   "net_margin": 1.39,
   "operating_expenses": 47241.0,
   "operating_income": 6618.0,
   "operating_margin": 3.01,
   "pretax_income": 4531.0,
   "revenue": 219603.0,
   "revenue_ttm": 846125.0,
   "revenue_yoy": -7.0
  },
  "2018Q1": {
   "cogs": 169471.0,
   "eps": -0.16,
   "eps_ttm": 0.99,
   "eps_yoy": 78.38,
   "gross_margin": 25.85,
   "gross_profit": 59070.0,
   "net_income": -3211.0,
   "net_income_ttm": 19986.0,
   "net_income_yoy": 77.53,
   "net_margin": -1.4,
   "operating_expenses": 48830.0,
   "operating_income": 10240.0,
   "operating_margin": 4.48,
   "pretax_income": -3732.0,
   "revenue": 228541.0,
   "revenue_ttm": 878947.0,
   "revenue_yoy": 16.77
  },
  "2018Q2": {
   "cogs": 172285.0,
   "eps": 1.43,
   "eps_ttm": 2.01,
   "eps_yoy": 248.78,
   "gross_margin": 27.57,
   "gross_profit": 65565.0,
   "net_income": 29608.0,
   "net_income_ttm": 41394.0,
   "net_income_yoy": 261.07,
   "net_margin": 12.45,
   "operating_expenses": 54032.0,
   "operating_income": 11533.0,
   "operating_margin": 4.85,
   "pretax_income": 38009.0,
   "revenue": 237850.0,
   "revenue_ttm": 911649.0,
   "revenue_yoy": 15.94
  },
  "2018Q3": {
   "cogs": 177809.0,
   "eps": 1.0,
   "eps_ttm": 2.42,
   "eps_yoy": 69.49,
   "gross_margin": 29.7,
   "gross_profit": 75129.0,
   "net_income": 22072.0,
   "net_income_ttm": 51521.0,
   "net_income_yoy": 84.78,
   "net_margin": 8.73,
   "operating_expenses": 55251.0,
   "operating_income": 19878.0,
   "operating_margin": 7.86,
   "pretax_income": 28025.0,
   "revenue": 252938.0,
   "revenue_ttm": 938932.0,
   "revenue_yoy": 12.09
  },
  "2018Q4": {
   "cogs": 156292.0,
   "current_assets": 750770.0,
   "current_liabilities": 360989.0,
   "current_ratio": 207.98,
   "debt_ratio": 45.2,
   "eps": 0.63,
   "eps_ttm": 2.9,
   "eps_yoy": 320.0,
   "equity": 498223.0,
   "equity_parent": 498223.0,
   "gross_margin": 29.47,
   "gross_profit": 65300.0,
   "net_income": 13960.0,
   "net_income_ttm": 62429.0,
   "net_income_yoy": 357.4,
   "net_margin": 6.3,
   "operating_expenses": 54184.0,
   "operating_income": 11116.0,
   "operating_margin": 5.02,
   "pretax_income": 17900.0,
   "revenue": 221592.0,
   "revenue_ttm": 940921.0,
   "revenue_yoy": 0.91,
   "roa_q": 1.54,
   "roa_ttm": 6.87,
   "roe_q": 2.8,
   "roe_ttm": 12.53,
   "total_assets": 909099.0,
   "total_liabilities": 410876.0
  },
  "2019Q1": {
   "cogs": 153572.0,
   "eps": 0.54,
   "eps_ttm": 3.6,
   "eps_yoy": 437.5,
   "gross_margin": 28.17,
   "gross_profit": 60228.0,
   "net_income": 11940.0,
   "net_income_ttm": 77580.0,
   "net_income_yoy": 471.85,
   "net_margin": 5.58,
   "operating_expenses": 53214.0,
   "operating_income": 7014.0,
   "operating_margin": 3.28,
   "pretax_income": 14207.0,
   "revenue": 213800.0,
   "revenue_ttm": 926180.0,
   "revenue_yoy": -6.45
  },
  "2019Q2": {
   "cogs": 160263.0,
   "eps": 0.66,
   "eps_ttm": 2.83,
   "eps_yoy": -53.85,
   "gross_margin": 30.08,
   "gross_profit": 68948.0,
   "net_income": 14476.0,
   "net_income_ttm": 62448.0,
   "net_income_yoy": -51.11,
   "net_margin": 6.32,
   "operating_expenses": 54062.0,
   "operating_income": 14886.0,
   "operating_margin": 6.49,
   "pretax_income": 19543.0,
   "revenue": 229211.0,
   "revenue_ttm": 917541.0,
   "revenue_yoy": -3.63
  },
  "2019Q3": {
   "cogs": 163885.0,
   "current_assets": 799800.0,
   "current_liabilities": 251146.0,
   "current_ratio": 318.46,
   "debt_ratio": 47.57,
   "eps": 0.89,
   "eps_ttm": 2.72,
   "eps_yoy": -11.0,
   "equity": 503984.0,
   "equity_parent": 503984.0,
   "gross_margin": 30.72,
   "gross_profit": 72672.0,
   "net_income": 19659.0,
   "net_income_ttm": 60035.0,
   "net_income_yoy": -10.93,
   "net_margin": 8.31,
   "operating_expenses": 53979.0,
   "operating_income": 18693.0,
   "operating_margin": 7.9,
   "pretax_income": 24222.0,
   "revenue": 236557.0,
   "revenue_ttm": 901160.0,
   "revenue_yoy": -6.48,
   "roa_q": 2.05,
   "roa_ttm": 6.25,
   "roe_q": 3.9,
   "roe_ttm": 11.91,
   "total_assets": 961177.0,
   "total_liabilities": 457193.0
  },
  "2019Q4": {
   "cogs": 170787.0,
   "current_assets": 844307.0,
   "current_liabilities": 285346.0,
   "current_ratio": 295.89,
   "debt_ratio": 47.53,
   "eps": 0.27,
   "eps_ttm": 2.36,
   "eps_yoy": -57.14,
   "equity": 523688.0,
   "equity_parent": 523688.0,
   "gross_margin": 28.86,
   "gross_profit": 69283.0,
   "net_income": 6036.0,
   "net_income_ttm": 52111.0,
   "net_income_yoy": -56.76,
   "net_margin": 2.51,
   "operating_expenses": 52079.0,
   "operating_income": 17204.0,
   "operating_margin": 7.17,
   "pretax_income": 7063.0,
   "revenue": 240070.0,
   "revenue_ttm": 919638.0,
   "revenue_yoy": 8.34,
   "roa_q": 0.6,
   "roa_ttm": 5.22,
   "roe_q": 1.15,
   "roe_ttm": 9.95,
   "total_assets": 998031.0,
   "total_liabilities": 474343.0
  },
  "2020Q1": {
   "cogs": 166291.0,
   "current_assets": 885035.0,
   "current_liabilities": 320046.0,
   "current_ratio": 276.53,
   "debt_ratio": 45.53,
   "eps": 0.41,
   "eps_ttm": 2.23,
   "eps_yoy": -24.07,
   "equity": 565978.0,
   "equity_parent": 565978.0,
   "gross_margin": 27.13,
   "gross_profit": 61899.0,
   "net_income": 9495.0,
   "net_income_ttm": 49666.0,
   "net_income_yoy": -20.48,
   "net_margin": 4.16,
   "operating_expenses": 50874.0,
   "operating_income": 11025.0,
   "operating_margin": 4.83,
   "pretax_income": 13034.0,
   "revenue": 228190.0,
   "revenue_ttm": 934028.0,
   "revenue_yoy": 6.73,
   "roa_q": 0.91,
   "roa_ttm": 4.78,
   "roe_q": 1.68,
   "roe_ttm": 8.78,
   "total_assets": 1039153.0,
   "total_liabilities": 473175.0
  },
  "2020Q2": {
   "cogs": 186904.0,
   "current_assets": 970626.0,
   "current_liabilities": 414529.0,
   "current_ratio": 234.15,
   "debt_ratio": 50.81,
   "eps": 0.95,
   "eps_ttm": 2.52,
   "eps_yoy": 43.94,
   "equity": 552075.0,
   "equity_parent": 552075.0,
   "gross_margin": 31.36,
   "gross_profit": 85379.0,
   "net_income": 23105.0,
   "net_income_ttm": 58295.0,
   "net_income_yoy": 59.61,
   "net_margin": 8.49,
   "operating_expenses": 53325.0,
   "operating_income": 32054.0,
   "operating_margin": 11.77,
   "pretax_income": 28904.0,
   "revenue": 272283.0,
   "revenue_ttm": 977100.0,
   "revenue_yoy": 18.79,
   "roa_q": 2.06,
   "roa_ttm": 5.19,
   "roe_q": 4.19,
   "roe_ttm": 10.56,
   "total_assets": 1122310.0,
   "total_liabilities": 570235.0
  },
  "2020Q3": {
   "cogs": 212122.0,
   "current_assets": 921234.0,
   "current_liabilities": 327330.0,
   "current_ratio": 281.44,
   "debt_ratio": 37.46,
   "eps": 0.95,
   "eps_ttm": 2.58,
   "eps_yoy": 6.74,
   "equity": 669406.0,
   "equity_parent": 669406.0,
   "gross_margin": 30.04,
   "gross_profit": 91093.0,
   "net_income": 24322.0,
   "net_income_ttm": 62958.0,
   "net_income_yoy": 23.72,
   "net_margin": 8.02,
   "operating_expenses": 55540.0,
   "operating_income": 35553.0,
   "operating_margin": 11.73,
   "pretax_income": 30659.0,
   "revenue": 303215.0,
   "revenue_ttm": 1043758.0,
   "revenue_yoy": 28.18,
   "roa_q": 2.27,
   "roa_ttm": 5.88,
   "roe_q": 3.63,
   "roe_ttm": 9.41,
   "total_assets": 1070415.0,
   "total_liabilities": 401009.0
  },
  "2020Q4": {
   "cogs": 202764.0,
   "current_assets": 957955.0,
   "current_liabilities": 327250.0,
   "current_ratio": 292.73,
   "debt_ratio": 34.07,
   "eps": 0.6,
   "eps_ttm": 2.91,
   "eps_yoy": 122.22,
   "equity": 726729.0,
   "equity_parent": 726729.0,
   "gross_margin": 30.81,
   "gross_profit": 90285.0,
   "net_income": 17936.0,
   "net_income_ttm": 74858.0,
   "net_income_yoy": 197.15,
   "net_margin": 6.12,
   "operating_expenses": 59014.0,
   "operating_income": 31271.0,
   "operating_margin": 10.67,
   "pretax_income": 28943.0,
   "revenue": 293049.0,
   "revenue_ttm": 1096737.0,
   "revenue_yoy": 22.07,
   "roa_q": 1.63,
   "roa_ttm": 6.79,
   "roe_q": 2.47,
   "roe_ttm": 10.3,
   "total_assets": 1102202.0,
   "total_liabilities": 375473.0
  },
  "2021Q1": {
   "cogs": 208099.0,
   "current_assets": 962784.0,
   "current_liabilities": 336241.0,
   "current_ratio": 286.34,
   "debt_ratio": 32.73,
   "eps": 0.75,
   "eps_ttm": 3.25,
   "eps_yoy": 82.93,
   "equity": 756055.0,
   "equity_parent": 756055.0,
   "gross_margin": 31.96,
   "gross_profit": 97763.0,
   "net_income": 22433.0,
   "net_income_ttm": 87796.0,
   "net_income_yoy": 136.26,
   "net_margin": 7.33,
   "operating_expenses": 63496.0,
   "operating_income": 34267.0,
   "operating_margin": 11.2,
   "pretax_income": 33800.0,
   "revenue": 305862.0,
   "revenue_ttm": 1174409.0,
   "revenue_yoy": 34.04,
   "roa_q": 2.0,
   "roa_ttm": 7.81,
   "roe_q": 2.97,
   "roe_ttm": 11.61,
   "total_assets": 1123864.0,
   "total_liabilities": 367809.0
  },
  "2021Q2": {
   "cogs": 274635.0,
   "current_assets": 1290705.0,
   "current_liabilities": 403502.0,
   "current_ratio": 319.88,
   "debt_ratio": 45.97,
   "eps": 0.93,
   "eps_ttm": 3.23,
   "eps_yoy": -2.11,
   "equity": 783231.0,
   "equity_parent": 783231.0,
   "gross_margin": 28.17,
   "gross_profit": 107709.0,
   "net_income": 27967.0,
   "net_income_ttm": 92658.0,
   "net_income_yoy": 21.04,
   "net_margin": 7.31,
   "operating_expenses": 66776.0,
   "operating_income": 40933.0,
   "operating_margin": 10.71,
   "pretax_income": 38500.0,
   "revenue": 382344.0,
   "revenue_ttm": 1284470.0,
   "revenue_yoy": 40.42,
   "roa_q": 1.93,
   "roa_ttm": 6.39,
   "roe_q": 3.57,
   "roe_ttm": 11.83,
   "total_assets": 1449599.0,
   "total_liabilities": 666368.0
  },
  "2021Q3": {
   "cogs": 241927.0,
   "current_assets": 1138569.0,
   "current_liabilities": 283852.0,
   "current_ratio": 401.11,
   "debt_ratio": 41.35,
   "eps": 0.71,
   "eps_ttm": 2.99,
   "eps_yoy": -25.26,
   "equity": 769806.0,
   "equity_parent": 769806.0,
   "gross_margin": 28.97,
   "gross_profit": 98672.0,
   "net_income": 21663.0,
   "net_income_ttm": 89999.0,
   "net_income_yoy": -10.93,
   "net_margin": 6.36,
   "operating_expenses": 69802.0,
   "operating_income": 28870.0,
   "operating_margin": 8.48,
   "pretax_income": 30033.0,
   "revenue": 340599.0,
   "revenue_ttm": 1321854.0,
   "revenue_yoy": 12.33,
   "roa_q": 1.65,
   "roa_ttm": 6.86,
   "roe_q": 2.81,
   "roe_ttm": 11.69,
   "total_assets": 1312570.0,
   "total_liabilities": 542764.0
  },
  "2021Q4": {
   "cogs": 245411.0,
   "current_assets": 1128408.0,
   "current_liabilities": 293825.0,
   "current_ratio": 384.04,
   "debt_ratio": 41.13,
   "eps": 0.52,
   "eps_ttm": 2.91,
   "eps_yoy": -13.33,
   "equity": 790088.0,
   "equity_parent": 790088.0,
   "gross_margin": 26.92,
   "gross_profit": 90383.0,
   "net_income": 15966.0,
   "net_income_ttm": 88029.0,
   "net_income_yoy": -10.98,
   "net_margin": 4.75,
   "operating_expenses": 74676.0,
   "operating_income": 15707.0,
   "operating_margin": 4.68,
   "pretax_income": 16788.0,
   "revenue": 335794.0,
   "revenue_ttm": 1364599.0,
   "revenue_yoy": 14.59,
   "roa_q": 1.19,
   "roa_ttm": 6.56,
   "roe_q": 2.02,
   "roe_ttm": 11.14,
   "total_assets": 1342105.0,
   "total_liabilities": 552017.0
  },
  "2022Q1": {
   "cogs": 271957.0,
   "current_assets": 1177487.0,
   "current_liabilities": 297992.0,
   "current_ratio": 395.14,
   "debt_ratio": 40.09,
   "eps": 0.75,
   "eps_ttm": 2.91,
   "eps_yoy": 0.0,
   "equity": 831804.0,
   "equity_parent": 831804.0,
   "gross_margin": 24.07,
   "gross_profit": 86221.0,
   "net_income": 22971.0,
   "net_income_ttm": 88567.0,
   "net_income_yoy": 2.4,
   "net_margin": 6.41,
   "operating_expenses": 71466.0,
   "operating_income": 14755.0,
   "operating_margin": 4.12,
   "pretax_income": 27618.0,
   "revenue": 358178.0,
   "revenue_ttm": 1416915.0,
   "revenue_yoy": 17.1,
   "roa_q": 1.65,
   "roa_ttm": 6.38,
   "roe_q": 2.76,
   "roe_ttm": 10.65,
   "total_assets": 1388503.0,
   "total_liabilities": 556699.0
  },
  "2022Q2": {
   "cogs": 217070.0,
   "current_assets": 1159588.0,
   "current_liabilities": 322935.0,
   "current_ratio": 359.08,
   "debt_ratio": 42.37,
   "eps": 0.44,
   "eps_ttm": 2.42,
   "eps_yoy": -52.69,
   "equity": 788829.0,
   "equity_parent": 788829.0,
   "gross_margin": 23.1,
   "gross_profit": 65217.0,
   "net_income": 13577.0,
   "net_income_ttm": 74177.0,
   "net_income_yoy": -51.45,
   "net_margin": 4.81,
   "operating_expenses": 65718.0,
   "operating_income": -501.0,
   "operating_margin": -0.18,
   "pretax_income": 16053.0,
   "revenue": 282287.0,
   "revenue_ttm": 1316858.0,
   "revenue_yoy": -26.17,
   "roa_q": 0.99,
   "roa_ttm": 5.42,
   "roe_q": 1.72,
   "roe_ttm": 9.4,
   "total_assets": 1368740.0,
   "total_liabilities": 579911.0
  },
  "2022Q3": {
   "cogs": 185521.0,
   "current_assets": 1029819.0,
   "current_liabilities": 397032.0,
   "current_ratio": 259.38,
   "debt_ratio": 34.56,
   "eps": 0.59,
   "eps_ttm": 2.3,
   "eps_yoy": -16.9,
   "equity": 810534.0,
   "equity_parent": 810534.0,
   "gross_margin": 22.02,
   "gross_profit": 52388.0,
   "net_income": 17971.0,
   "net_income_ttm": 70485.0,
   "net_income_yoy": -17.04,
   "net_margin": 7.55,
   "operating_expenses": 63292.0,
   "operating_income": -10904.0,
   "operating_margin": -4.58,
   "pretax_income": 21860.0,
   "revenue": 237909.0,
   "revenue_ttm": 1214168.0,
   "revenue_yoy": -30.15,
   "roa_q": 1.45,
   "roa_ttm": 5.69,
   "roe_q": 2.22,
   "roe_ttm": 8.7,
   "total_assets": 1238635.0,
   "total_liabilities": 428101.0
  },
  "2022Q4": {
   "cogs": 179301.0,
   "eps": -0.28,
   "eps_ttm": 1.5,
   "eps_yoy": -153.85,
   "gross_margin": 23.84,
   "gross_profit": 56118.0,
   "net_income": -8634.0,
   "net_income_ttm": 45885.0,
   "net_income_yoy": -154.08,
   "net_margin": -3.67,
   "operating_expenses": 56831.0,
   "operating_income": -713.0,
   "operating_margin": -0.3,
   "pretax_income": -12915.0,
   "revenue": 235419.0,
   "revenue_ttm": 1113793.0,
   "revenue_yoy": -29.89
  },
  "2023Q1": {
   "cogs": 186198.0,
   "current_assets": 1056941.0,
   "current_liabilities": 469896.0,
   "current_ratio": 224.93,
   "debt_ratio": 37.87,
   "eps": 0.16,
   "eps_ttm": 0.91,
   "eps_yoy": -78.67,
   "equity": 802343.0,
   "equity_parent": 802343.0,
   "gross_margin": 24.72,
   "gross_profit": 61127.0,
   "net_income": 4944.0,
   "net_income_ttm": 27858.0,
   "net_income_yoy": -78.48,
   "net_margin": 2.0,
   "operating_expenses": 58098.0,
   "operating_income": 3029.0,
   "operating_margin": 1.22,
   "pretax_income": 4607.0,
   "revenue": 247325.0,
   "revenue_ttm": 1002940.0,
   "revenue_yoy": -30.95,
   "roa_q": 0.38,
   "roa_ttm": 2.16,
   "roe_q": 0.62,
   "roe_ttm": 3.47,
   "total_assets": 1291327.0,
   "total_liabilities": 488984.0
  },
  "2023Q2": {
   "cogs": 201433.0,
   "current_assets": 1052680.0,
   "current_liabilities": 489938.0,
   "current_ratio": 214.86,
   "debt_ratio": 40.29,
   "eps": 0.46,
   "eps_ttm": 0.93,
   "eps_yoy": 4.55,
   "equity": 753614.0,
   "equity_parent": 753614.0,
   "gross_margin": 24.2,
   "gross_profit": 64307.0,
   "net_income": 13960.0,
   "net_income_ttm": 28241.0,
   "net_income_yoy": 2.82,
   "net_margin": 5.25,
   "operating_expenses": 62483.0,
   "operating_income": 1824.0,
   "operating_margin": 0.69,
   "pretax_income": 15794.0,
   "revenue": 265740.0,
   "revenue_ttm": 986393.0,
   "revenue_yoy": -5.86,
   "roa_q": 1.11,
   "roa_ttm": 2.24,
   "roe_q": 1.85,
   "roe_ttm": 3.75,
   "total_assets": 1262078.0,
   "total_liabilities": 508464.0
  },
  "2023Q3": {
   "cogs": 254789.0,
   "eps": 0.89,
   "eps_ttm": 1.23,
   "eps_yoy": 50.85,
   "gross_margin": 22.78,
   "gross_profit": 75153.0,
   "net_income": 27277.0,
   "net_income_ttm": 37547.0,
   "net_income_yoy": 51.78,
   "net_margin": 8.27,
   "operating_expenses": 63001.0,
   "operating_income": 12152.0,
   "operating_margin": 3.68,
   "pretax_income": 29924.0,
   "revenue": 329942.0,
   "revenue_ttm": 1078426.0,
   "revenue_yoy": 38.68
  },
  "2023Q4": {
   "cogs": 179315.0,
   "eps": -0.32,
   "eps_ttm": 1.19,
   "eps_yoy": -14.29,
   "gross_margin": 24.51,
   "gross_profit": 58220.0,
   "net_income": -9794.0,
   "net_income_ttm": 36387.0,
   "net_income_yoy": -13.44,
   "net_margin": -4.12,
   "operating_expenses": 55530.0,
   "operating_income": 2690.0,
   "operating_margin": 1.13,
   "pretax_income": -15069.0,
   "revenue": 237535.0,
   "revenue_ttm": 1080542.0,
   "revenue_yoy": 0.9
  },
  "2024Q1": {
   "cogs": 170767.0,
   "eps": 0.51,
   "eps_ttm": 1.54,
   "eps_yoy": 218.75,
   "gross_margin": 25.77,
   "gross_profit": 59290.0,
   "net_income": 15553.0,
   "net_income_ttm": 46996.0,
   "net_income_yoy": 214.58,
   "net_margin": 6.76,
   "operating_expenses": 58631.0,
   "operating_income": 659.0,
   "operating_margin": 0.29,
   "pretax_income": 18600.0,
   "revenue": 230057.0,
   "revenue_ttm": 1063274.0,
   "revenue_yoy": -6.98
  },
  "2024Q2": {
   "cogs": 189030.0,
   "eps": 0.63,
   "eps_ttm": 1.71,
   "eps_yoy": 36.96,
   "gross_margin": 29.06,
   "gross_profit": 77416.0,
   "net_income": 19239.0,
   "net_income_ttm": 52275.0,
   "net_income_yoy": 37.82,
   "net_margin": 7.22,
   "operating_expenses": 61843.0,
   "operating_income": 15573.0,
   "operating_margin": 5.84,
   "pretax_income": 24844.0,
   "revenue": 266446.0,
   "revenue_ttm": 1063980.0,
   "revenue_yoy": 0.27
  },
  "2024Q3": {
   "cogs": 202615.0,
   "current_assets": 1071488.0,
   "current_liabilities": 236018.0,
   "current_ratio": 453.99,
   "debt_ratio": 36.16,
   "eps": 0.12,
   "eps_ttm": 0.94,
   "eps_yoy": -86.52,
   "equity": 873438.0,
   "equity_parent": 873438.0,
   "gross_margin": 26.26,
   "gross_profit": 72137.0,
   "net_income": 3868.0,
   "net_income_ttm": 28866.0,
   "net_income_yoy": -85.82,
   "net_margin": 1.41,
   "operating_expenses": 58407.0,
   "operating_income": 13730.0,
   "operating_margin": 5.0,
   "pretax_income": 6062.0,
   "revenue": 274752.0,
   "revenue_ttm": 1008790.0,
   "revenue_yoy": -16.73,
   "roa_q": 0.28,
   "roa_ttm": 2.11,
   "roe_q": 0.44,
   "roe_ttm": 3.3,
   "total_assets": 1368231.0,
   "total_liabilities": 494793.0
  },
  "2024Q4": {
   "cogs": 192548.0,
   "current_assets": 1093880.0,
   "current_liabilities": 235106.0,
   "current_ratio": 465.27,
   "debt_ratio": 36.04,
   "eps": 0.44,
   "eps_ttm": 1.7,
   "eps_yoy": 237.5,
   "equity": 882156.0,
   "equity_parent": 882156.0,
   "gross_margin": 22.58,
   "gross_profit": 56142.0,
   "net_income": 14059.0,
   "net_income_ttm": 52719.0,
   "net_income_yoy": 243.55,
   "net_margin": 5.65,
   "operating_expenses": 61995.0,
   "operating_income": -5853.0,
   "operating_margin": -2.35,
   "pretax_income": 15422.0,
   "revenue": 248690.0,
   "revenue_ttm": 1019945.0,
   "revenue_yoy": 4.7,
   "roa_q": 1.02,
   "roa_ttm": 3.82,
   "roe_q": 1.59,
   "roe_ttm": 5.98,
   "total_assets": 1379235.0,
   "total_liabilities": 497079.0
  },
  "2025Q1": {
   "cogs": 219628.0,
   "current_assets": 1084150.0,
   "current_liabilities": 202547.0,
   "current_ratio": 535.26,
   "debt_ratio": 34.87,
   "eps": 0.45,
   "eps_ttm": 1.64,
   "eps_yoy": -11.76,
   "equity": 908225.0,
   "equity_parent": 908225.0,
   "gross_margin": 23.51,
   "gross_profit": 67522.0,
   "net_income": 14508.0,
   "net_income_ttm": 51674.0,
   "net_income_yoy": -6.72,
   "net_margin": 5.05,
   "operating_expenses": 57473.0,
   "operating_income": 10049.0,
   "operating_margin": 3.5,
   "pretax_income": 17018.0,
   "revenue": 287150.0,
   "revenue_ttm": 1077038.0,
   "revenue_yoy": 24.82,
   "roa_q": 1.04,
   "roa_ttm": 3.71,
   "roe_q": 1.6,
   "roe_ttm": 5.69,
   "total_assets": 1394424.0,
   "total_liabilities": 486199.0
  },
  "2025Q2": {
   "cogs": 216284.0,
   "current_assets": 1012130.0,
   "current_liabilities": 241575.0,
   "current_ratio": 418.97,
   "debt_ratio": 40.29,
   "eps": -0.83,
   "eps_ttm": 0.18,
   "eps_yoy": -231.75,
   "equity": 777611.0,
   "equity_parent": 777611.0,
   "gross_margin": 21.78,
   "gross_profit": 60233.0,
   "net_income": -26694.0,
   "net_income_ttm": 5741.0,
   "net_income_yoy": -238.75,
   "net_margin": -9.65,
   "operating_expenses": 50501.0,
   "operating_income": 9732.0,
   "operating_margin": 3.52,
   "pretax_income": -32720.0,
   "revenue": 276517.0,
   "revenue_ttm": 1087109.0,
   "revenue_yoy": 3.78,
   "roa_q": -2.05,
   "roa_ttm": 0.44,
   "roe_q": -3.43,
   "roe_ttm": 0.74,
   "total_assets": 1302396.0,
   "total_liabilities": 524785.0
  },
  "2025Q3": {
   "cogs": 223762.0,
   "current_assets": 961967.0,
   "current_liabilities": 440241.0,
   "current_ratio": 218.51,
   "debt_ratio": 37.5,
   "eps": 0.49,
   "eps_ttm": 0.55,
   "eps_yoy": 308.33,
   "equity": 815225.0,
   "equity_parent": 815225.0,
   "gross_margin": 23.06,
   "gross_profit": 67047.0,
   "net_income": 15744.0,
   "net_income_ttm": 17617.0,
   "net_income_yoy": 307.03,
   "net_margin": 5.41,
   "operating_expenses": 55974.0,
   "operating_income": 11073.0,
   "operating_margin": 3.81,
   "pretax_income": 18320.0,
   "revenue": 290809.0,
   "revenue_ttm": 1103166.0,
   "revenue_yoy": 5.84,
   "roa_q": 1.21,
   "roa_ttm": 1.35,
   "roe_q": 1.93,
   "roe_ttm": 2.16,
   "total_assets": 1304336.0,
   "total_liabilities": 489111.0
  },
  "2025Q4": {
   "cogs": 215467.0,
   "current_assets": 1043148.0,
   "current_liabilities": 413854.0,
   "current_ratio": 252.06,
   "debt_ratio": 34.1,
   "eps": 0.37,
   "eps_ttm": 0.48,
   "eps_yoy": -15.91,
   "equity": 883725.0,
   "equity_parent": 883725.0,
   "gross_margin": 20.35,
   "gross_profit": 55034.0,
   "net_income": 11939.0,
   "net_income_ttm": 15497.0,
   "net_income_yoy": -15.08,
   "net_margin": 4.41,
   "operating_expenses": 52508.0,
   "operating_income": 2526.0,
   "operating_margin": 0.93,
   "pretax_income": 11941.0,
   "revenue": 270501.0,
   "revenue_ttm": 1124977.0,
   "revenue_yoy": 8.77,
   "roa_q": 0.89,
   "roa_ttm": 1.16,
   "roe_q": 1.35,
   "roe_ttm": 1.75,
   "total_assets": 1341096.0,
   "total_liabilities": 457371.0
  },
  "2026Q1": {
   "cogs": 229755.0,
   "current_assets": 1106984.0,
   "current_liabilities": 420483.0,
   "current_ratio": 263.26,
   "eps": 0.72,
   "eps_ttm": 0.75,
   "eps_yoy": 60.0,
   "equity_parent": 937872.0,
   "gross_margin": 21.77,
   "gross_profit": 63924.0,
   "net_income": 23944.0,
   "net_income_ttm": 24933.0,
   "net_income_yoy": 65.04,
   "net_margin": 8.15,
   "operating_expenses": 53107.0,
   "operating_income": 10817.0,
   "operating_margin": 3.68,
   "pretax_income": 27485.0,
   "revenue": 293679.0,
   "revenue_ttm": 1131506.0,
   "revenue_yoy": 2.27
  }
 }
}